{"relation":["http://data.theeuropeanlibrary.org/Collection/a0599","Notice du catalogue : http://catalogue.bnf.fr/ark:/12148/cb327877302","Europeana Newspapers","http://data.theeuropeanlibrary.org/Collection/a0142"],"rights":["domaine public","public domain","http://creativecommons.org/publicdomain/mark/","This metadata record is licensed under: http://creativecommons.org/publicdomain/zero/1.0/"],"format":["[OCR confidence] 0,409523"],"date":["1914-10-05"],"type":["Newspaper Issue","texte","text","publication en série imprimée","printed serial","Text"],"creator":["Parti communiste français"],"publisher":["L'Humanité (Paris)","L'Humanité (Saint-Denis)"],"title":["L'Humanité"],"source":["Bibliothèque nationale de France","http://gallica.bnf.fr/ark:/12148/bpt6k253967x","Metadata aggregated by The European Library","Metadata provided by National Library of France "],"contributor":["Jaurès, Jean (1859-1914). Directeur de publication"],"description":["1914/10/05 (Numéro 3823).","fre\n            Latn"],"contentAsText":["C VZIEME A> T XUE — 3^3\n6 Pages — 5 e\nfîLS spéciaux ifosores adresse paris (2\") : 142, ru® Montmart» adresse télégraphique: humanité-paris T éléphone : GUTENBERG I Q ^Ies PUBLICITÉ annonces M3, Au» MorttmwtM, «43\nÏ .UNDI 5 OCTOBRE IMT 6 Pages — 5 e Le journal l'HUMANITÊ est vendu en Belgique OT p.i A ABONNEMENTS Suis frais doua tout, les Bureaux de Poste li.t 6 nais 3noi.i txom rt Seint^-Oiae { 18fr. 9 fr. 4 50 160 °ePcSSS^ } 21 . 10 60 6 28 1 7» Union postale t 31 • tS 50 9 » ® •\nJOURNAL SOCIALISTE\nFondateur s «JEAN JAUIRÈS\nLE TERME APPROCHE !\nPar le nombre énorme de lettres qui continuent A parvenir à VHumanité au sujet du terme d'octobre, il apparaît nécessaire de rappeler les décrets minis tériels fixant les devoirs et les droits de chacun. Il y a eu trois arrêtés qui se sont com plétés > : celui du 14 aoi).t, celui du 1 er septembre, celui du 27 septembre. Ce dernier tient compte en une mesure re lative des résolutions du groupe des dé-, putésde Paris. ' ' Petits loyers (i .000 francs et au-des sous). -r- II . est entendu que pour les pe tits loyers. la prorogation de 90 jours va de \"soi. Donc, les 8 et 15 octobre, les locatai res de cette catégorie pourront \"ne pas payer leur terme qui restera dû. Ils au ront 90 jours pour s'acquitter, si d'ici là, aucune mesure nouvelle n'est inter venue. L oyers au-dessus de 1.000 francs. — Pour ceux-là, il faut envoyer au pro priétaire une lettre recommandée l'avi sant qu'on est hors d'état de payer tout ou partie du lover, ou en faire_ la dé claration verbale ou écrite au juge de paix du quartier. Sont exceptés de cette déclaration les mobilisés et les patentés, industriels ou commerçants. Pour les loyers au-dessus de 1.000 francs qui sont dus par des personnes n'étant ni patentés ni mobilisées, si on ne peut les payer, il faut prendre les précautions indiquées par -as décrets, c'est-à-dire écrire au propriétaire ou au juge de paix. Si les propriétaires veulent absolu ment être pavés par les locataires de cette dernière catégorie, ils pourront protester près du juge contre leur dé claration. C'est le juge de paix qui, aimablement, tranchera en équité. Ceci, répétons-le, pour les loyers au-dessus de 1 .000 francs dus par des non mobilisés et des non patentés. Car pour les autres, le. fait de refuser la quittance au pro priétaire suffit aux termes du décret. ' On paiera plus tard. Mais ici, nouvelle question ! Si on me représente en janvier mes deux quittances à la t'ois, je serai encore moins en état cle m'acquitter qu'aujour d 'hui. N'anticipons pas ! Commençons par ne pas payer le terme d'octobre ; c'est le seul objet visé par les décrets actuels. Dans la suite, on verra. Il est sûr qu'il faudra prendre des arrangements pour sauvegarder tous les droits. Mais un dé cret ne'peut que suspendre des paie ments. ... Pour annuler des contrats, il faut une îdL. Cette loi interviendra à son heure, et elle donnera satisfaction aux intérêts des travailleurs. Nous ferons, à ce mo ment-là, tous nos efforts pour qu'il en Boit ainsi. MARCEL CACHIN\nA propos DES Atrocités\nLes atrocités commises par les ar mées allemandes ne peuvent plus faire doute pour personne, même à l'étranger, quelles que soient les précau tions prises par l'Allemagne pour éga rer l'opinion publique sur ce point com me sur d'autres. Naturellement, l'Allemagne s'est dé fendue au regard de l'opinion pu blique. Elle a tantôt nié, tantôt essayé d'atténuer les faits dont elle était accu sée, comme elle a pu — on se tire d'af faire comme on peut, a dit M. de Beth- mann-Hollweg. Elle n'a pas pris garde par là que si les faits devenaient prouvés, elle en soulignait. le caractère' odieux puis qu'elle sentait le besoin de paraître les repousser comme indignes d'une na tion civilisée. Mais elle ne s'est pas, seulement dé fendue. Elle a accusé, et elle a présenté les nations alliées comme l'ayant mise, elle, par leurs procédés, ' dans l'obliga tion de Drendre des mesures de dévasta tion et de meurtre raffiné. -Un de nos amis me signale par exemnle un article, du reste déià vieux, des Hamburger Nachrirhten, où on ac cuse les Français de s'être servis de hallp=! dum-dum. et oui donne un luxe de détails destiné à authentiquer l'accu sation : Ces bîïU.es infâmes étalent rangées en pe tits paquets entourés d'un fort napier vert, ficelés, marqués d'une estampille. Le tout d'une manière tout à fait officielle. Des cais ses remplies de ces paquets ont été trouvées à Longwy, Montmédy et dans les. dépôts d'autres places françaises. Et puis voici le-bout de l'oreille : Cette culpabilité appelle le châtiment. Déjà on a annoncé que notre direction mi litaire se voit contrainte à' des cdntre^mestires pour réagir contre l'emploi de ces engins infâmes. Comme le dit notre ami : La tactique est claire, attribuer à l'adversaire les pires moyens pour exciter les passions et justifier d'avance tous les crimes. Faut-il donc qu'on aille ainsi de cri mes en crimes, d'atrocités en atrocités plus horribles, de férocités en férocités plus implacables, sans qu'il y ait un moyen de mettre un terme à' ce cres cendo sinistre ?■ Le 23 août, *VHumanité publiait une\nLA LUTTE BAT SOS PLEIN\nNom.avons « pipgressé ; ! et pris des tranchées\nLa Bataille\nDU\nNiémen\nLA DÉCLARATION PIERRE KROPOTKINE\n.(Communiqué officiel, h octobre, 15 h.) A NOTRE AILE GAUCHE Après avoir repoussé toutes ies attaques ennemies, nous avons repris l'offensive sur plusieurs points ; sur tes autres, nos positions sont sensiblement maintenues. AU CENTRE Rien à signaler jusqu'à l'Argonne. Dans l'Argonne, nous avons refoulé l'en nemi vers le Nord. Dans la Woëvre méridionale, nous pro gressons, mais très lentement. A NOTRE AILE DROITE Lorraine et Vosges, rien de nouveau. 'Va (iCommuniqué officiel, 4 octobre, 23 h.). 1° A notre aile gauche, fa lutte bat son plein dans la région d'Arras, sans qu'au cune décision ait été encore obtenue. L'action a été moins violente entre la vallée supérieure de S'Ancre et la Somme et entre la Somme et l'Oise.\nNous avons progressé da«3 la région de ! niées.\nSoissons où des tranchées ennemies ont été prises. 2° Sur presque tout le reste du front s l'accalmie déjà signalée persiste. En Woëvre, nous avons fait quelque pro grès entre Apremont et la Meuse et sur le Rupt de Mad. M. POINQARE SUR LE FRONT Bordeaux, 4 octobre. — Depuis le début des hostilités, le président de la Républi que avait exprimé l'intention de rendre vi site aux armées et de leur porter ses féli citations. Ï1 en avait été empêché jusqu'ici, tantôt par la nécessité de présider quoti diennement le Conseil des ministres, tari tôt par le désir de l'autorité militaire qui ne jugeait pas. le moment favorable, à la réalisation de ce projet. . Les circonstances permettent aujour d'hui ce déplacement. M, Poincaré a quitté Bordeaux à midi en automobile, accompagné de MM. Vi vian!, président du conseil, et Millerand, ministre de la guerre, se rendant aux ar-\ntravers les cruautés de la bataipe, /le tels souffles d'humanité, faut-il que nous désespérions d'arracher à la lutte son caractère de férocité aggravée ? Ne suffira-t-il pas d'être résolus au combat jusqu'à la mort, sans exacerber la soùf- france et sans meurtrir jusqu'au fond la conscience humaine ?.. Voilà pourquoi, pour ma part, j'ap puie ici l'initiative de M. Seippel et celle de notre correspondant du 23 août. PIERRE RENAUDEL.\n» HE itïfclS m sis umm\nlettre d'un de oue\nes lecteurs ainsi- con-\nD1X1EME LISTE Nous prions les camarades habitant les localités où des blessés sont en traitement de les visiter et de nous donner des nou velles,'nous pourrons ainsi les communi quer à leurs familles. Les lettres doivent être adressées au citoyen Gaston Lévy, à l'Humanité. NOS MORTS Clovis Jor elle, de la section de Cour celle les-Gisors (Oise), tué au combat d'Etrc- pilly, le 7 septembre. Gaston Bourguigneaa, instituteur à Lan- geais, membre de la section de Tours, tué aux environs de Nancy. NOS BLESSÉS . Pastouraud, de la section d'Issy-les-Mou lineaux, biessé d la cheville et au genou, en traitement à Tarascon. Deyre, de la section de Lormont (Gi ronde), blessé à la caisse, à la bataille de la Marne. Elluin, instituteur à Bayeux, secrétaire ie.la section syndicale, membre du groupe te Caen, blessé dans les combats du Nord. Bourriique, membre de la section de Caen, blessé au pied, dans les combats de l'Aisne, en traitement à l'hôpital de Pour- ville (Seine-Inférieure). Catherine, graveur, membre du groupe de Caen, blessé, au combat de la Marne. Madiot, de la Fédération des Alpes-Mari times, blessé au pied dans les combats du Nord, en traitement au lycée de Caen. Schumacher, camarade de l'imprimerie du > journal, blessé* d'un éclat d'obus, en Lorraine, en traitement à Nîmes (Gard). Albert Anseaumls, trésorier du groupe de preux, soldat au- 301* régiment d'infante rie, blessé au bras gauche, dans la Meuse, ! Maurice Chevallier, instituteur d. Sotte- mille, blessé à la bataille de l'Aisne, en traitement à l'hôpital de Fontainebleau. Emile Pingcnot, fils de notre camarade II: Ping enott, membre de la section de Môntrouge, 104° régiment d'infanterie, blessé le 22 ao-ât, en Belgique. ; Anatole Gallemant, membre de la sec tion d'Amouville-lès-Gonesse (S.-et-O .), 72 e d'infanterie, blessé a,us jambes et ou bras, en traitement à Avignon. Fradin, instituteur à Saint-Dep .s, mem bre de la 17\" ifection, 89° régiment d'infan terie, blessé à la cuisse, à Monlfaucon {Lorraine). Chalve, instituteur, membre de la sec.- don de Puteaux, 276 a régiment d'infanterie, en traitement d Rodez. Vidaud, membre de la 13? section, sol dat au 335\" régiment d'infanterie, blessé d'une balle à la hanche, d Saint-Jean-de- liuzy. Repart au feu. Lucien Gompel, de la 18° section, blessé d Forges (Meuse). René Gumpel, de la 18® section, blessé à Virto-n (Belgique). Cannone, sergent, membre de la section de Waitignies-Templemars, blessé à la main, d Etain, en traitement à Toulouse. Lucien Boes, instituteur à Saint-Denis, membre de la 19° section, lieutenant, blessé au bras, sous Nancy. Real, instituteur d Saint-Denis, en trai tement à Pau.\n. Ne. serait-il pas possible, tant en droit in ternational. qu'au point de vue militaire, de demander à des pays neutres, puisque en reste encore, de servir la cause âè l'huma nité et .de la civilisation en fournissant des hommes autorisés, de notoriété mondiale «t de, moralité civique éprouvée, qui fonction neraient comme commissaires enquêteurs 7 Us prêteraient serment de ne communiquer aucune- dépêche relative aux opérations mi litaires, et des précautions pourraient d'ail leurs être prises pour les mettre dans l'im possibilité matérielle de le Aiire. Us sui vraient à distancé les armées, et, sur l'invi tation du commandement militaire ou de la population civile, se rendraient sur les lieux pour , y enquêter et faire un rapport.\nLa Situation Militaire\nLES TROUPES ALLEMANDES AURAIENT 400,000 HOMMES HORS DE COMBAT Londres, 4 octobre. — Le rédactaur mili taire du Times, après avoir passé en revue les événements de ces deux mois de guerre, constate que la retraite allemande fait apparaître à tous « l'échec de l'abjecte en treprise initiale de l'Allemagne •>. Ii évalue, au minimum, à quatre cent milles hommes les pertes allem tndes sur le front ouest. - iEn/ce qui. concerne l'avenir, dit-il, nous . ne. devons avoir aucune illusion sur les. wndi: tions dures et pénibles qui attendent tous les alliés dans. leur lutte contre l'Allemagne, ré duite à la : défensive. Par conséquent, les Alliés doivent prendre des mesures eh prévi sion d'une longue guerre.\nDepuis, en Suisse, M. Paul Seippel, l'une des personnalités les plus consi dérables du monde littéraire suisse, a écrit djns le Journal de Genève deux articles sur la Guerre et le Droit, où il rappelle les violations successives du droit et de la Conférence de la Haye commises par les Allemands : neutralité belge, destruction de villes ouvertes. Il examine la question de l'emploi des balles dum-dum, l'ordre donné aux troupes autrichiennes de tout détruire en Serbie. M, Paul Seippel écrit enfin : Ce qu'il nous importe, à. nous,neutres, c'est qu'il ne se crée pas, peu à peu, un nouveau droit de guerre, implacable, contraire aux stipulations les plus formelles des conven tions de la Haye, signées par toutes les puis sances et qui ne serait pas autre chose qu 'une barbarie administrative, doublement' odieuse parce qu'elle serait préméditée. Il y a là une question sur laquelle nçus avons le droit et le. de voir de parler, haut..\nEn Belgique\nLA LUTTE AUTOUR D'ANVERS Anvers, 4 octobre. — (Officiel.) — La si tuation de la position fortifiée d'Anvers- est stationnaire. Amsterdam, 3 octobre. — Une dépêche adressée d'Anvers au Handelsblad an nonce que le fort de Waelhem est tou jours aux mains des Beiges, qui occupent de i'ôrtea positions au nord de la Nèthe. Les Allemands-n'ont pas essayé cle forcer le passage du fleuve. , * Des drapeaux flottent sur l'hôtel de ville et sur lès flèches dés églises, afin d'indi quer que ces bâtiments sont des monu ments historiques,\nM. Paul Seippel conclut, lui aussi, par l'idée d'une commission de contrôlé ou d'enquête des neutres. On me dit que dès maintenant, en Suisse, on a examiné l'application de cette proposi tion. Une telle commission ne peut as surément, fonctionner que si- toutes les puissances belligérantes en acceptent, le principe. Mais quel est donc le gouvernement qui oserait proclamer à la face du monde qu'il se refuse à laisser vérifier ses accusations ou celles qui sont portées contre lui ? Celui-là ne se con damnerait-il pas par là même, et ne prononcerait-il pas sur lui-même l'aveu de culpabilité le plus clair ? Ce n'est pas la .^France en tout cas, -—ni ses alliés — qui s'y opposera, nous en avons la ferme conviction, et elle s'honorera en faisant un bon accueil à cette tentative, si elle prend corps. Il ne s'agit pas de diminuer la vo lonté de combattre jusqu'à la victoire, mais nous avons bien le droit d'essayer de chasser le cauchemar d'atrocités où nous nous débattons. ; Il subsiste bien quelque pitié par le monde. Hier en core, on me contait cet épisode : Les nôtres avaient combattu avec leur en train coutumier. En face d'eux, la Iran chée' allemande était devenue silen cieuse. Notre 75 avait accompli son œuvre. Nos soldats avançaient {dans la tranchée, soixante-quatre cadavres mar quaient la défaite de l'ennemi. Mais parmi ceux-là. deux hommes vivaient encore. Ils tendaient leurs mains sup pliantes. Le spectacle était si poignant, que lles larmes mêlées , coulèrent, lar mes d'Allemands, larmes de Français. Larmes des vaincus, larmes des vain queurs. Ah I puisqu'il y a encore, à\nJ'ai reçu hier la visite de mon am' X..., ancien rédacteur militaire de la Tribune Russe, qui, dès le début de la gtferre, s'était engagé dans l'armée française comme soldat volontaire et qui dans l'es pace d'un mois a bu conquérir, avec ■ l'es time de ses chefs,' le grade de sergent d'abord, celui de lieutenant ensuite. Ils sont des centaines et des centaines ces réfugiés politiques russes qui, à l'heure où j'écris ces lignes, vont au feu Mais parmi eux je dois distinguer particulière ment . cette compagnie de « républicains russes » que X... va mener au feu et où je compte tant de camarades socialistes ré volutionnaires. X..., venu pour me dire adieu, au nom de quatre-vingts socialistes républicains russes, m'a raconté avec quel enthou siasme, avec quel amour ardent de la France cette compagnie va au combat. Nous, voulons combattre et mourir, avec- cette idée que la France sortira victorieuse de cette épreuve formidable. Nous sommés et restons des adversaires irréconciliables du tsarisme, .contre lequel nous avons lutté. en. risquant et notre liberté et notre vie. . Nous, avons parmi > nous des évadés des ba gnes sibériens... Mais nous avons la ferme conviction que le salut de la France est le salut de la civilisaJioni du droit, de 1-a li berté, de l'indépendance des peuples. C'est le salut de la Russie qui sortira de cette guerre, grandie pour marcher d'un tuas accéléré Vers la réalisation de notre idéal socialiste et ré volutionnaire. Que nos camarades socialistes et, russes qui vont au feu pour défendre l'intégrité du territoire de la France immortelle soient tranquilles. Tout en concentrant .nos efforts, notre pensée, notre volonté sur la seule pensée -de l'heure actuelle— la vic toire de la France — nous ne perdrons pas île,.vue un seul instant la lutte générale à laquelle nous avons consacré notre vie. La victoire de, la France sera aussi celle de la Russie révolutionnaire et de l'Inter nationale. Nous en -prenons l'engagement solennel. . ë.. Roubanovîtch. - -t- ut -r lu Vendeurs de \"l'anuiU\"\nAujourd'hui, nous continuerons ù rece voir les inscriptions pour la vente du jour- lal de demain en grande banlieue et d n nris. veut s'inscrire jusqu'à cinq heures du soir.\nJe me souviens qu'au moment de la mobilisation générale, à mes deux fils qui devaient aller se battre pour défen dre nos foyers, la France républicaine et la civilisation universelle, ie leur di sais : « Mes enfants, puisqu'il y a sur la terre des monstres pour dédancher la guerre dans toute l'Europe, je ne sou haite qu'une chose, c est que ce soit le bon droit qui triomphe. Mais quel que soit le .sort de nos armes, ne leis rougis- sez > jamais avec le sans- des blessés, des vieillards, des gens désarmés, des fem mes et des enfants. Songez que si c'est contre Guillaume et François-Joseph que vous allez.vous battre, ce n'est pas contre leurs peuples. Ne ■ soyez jamais des assassins ni des lâches. » Je n'eus pas besoin d'en dire davan tage-: j'étais sûr d'avoir été' compris. De l'un, je n'ai pas encore de nou velles, mais de l'autre, je sais qu'il est biessé. J'ai pu le voir et il ne mourra pas de la balle allemande qu'il a re çue. Mais ce qui' m'a f$it . le plus grand plaisir, c'est la lettre de ce blessé, lettre dans laquelle il m'annonce sa blessure tout en me rassurant et tout en formu lant l'espoir que cette .guerre terrible est- la dernière et qu'après c'est la fra ternité— le mot y est — qui régnera sur le monde. Il n'a même pas une parole de haine contre les Allemands. C'est qu'il sait bien que le peuple allemand n'est pour rien dans ce crime monstrueux. La presse française nous entretient — je n'oserai pas dire môme avec trop de complaisance par peur d'être traité de Prussien des cruautés alleman des. Et pourquoi ? .C'est en racontant ces horreurs, que certains journaux ont eftraye les gens, créé de sottes paniques et surexcité les esprits au point que, dans certains en droits, lorsqu'on voyait passer des pri sonniers allemands, les froussards, pré cisément, se mettaient des centaines à les injurier et à les menacer. Oui, certes, il y a eu — et il y a en core — dans les cohort.es de Guillau me II des soldats assez.lâches et assez vils pour pilier et incendier partout où ils passent, pour se conduire avec la dernière bestialité envers dés femmes et des enfants, pour faire sans raison le plus de mal qu'ils peuvent. Leux-là, on peut se demander s'ils ont une mère, des sœurs, des frères une femme, des enfants, s'ils sont bien d une nation de l'Europe, du monde ci vilisé. On se demande- même comment il peut se trouver dans l'armée allemande des chefs qui laissent faire --- voire qui ordonnent — ces monstrueux for faits. N'ont-ils jamais pensé, ces miséra bles, que le sort des armes en permet tant aux nôtres de les poursuivre à leur tour dans leur pays, leurs mères, leurs sœurs, Jes femmes et les enfants pour raient etre les innocentes victimes de la vengeance des Belges et des Français ? Pourquoi donc se sont-ils conduits en abominables bandits ? Cependant ce n'est pas l'AUemarae magne des quatre millions de so cialistes 'Allemagne oui fera bientôt sa République, qui doit souffrir les « vepres siciliennes », la vengeance de nos ,soldats victorieux, c'est la ka'ser et sa bande. Non, vaillants soldats de la généreuse France, de la glorieuse Belgique, de la noble Angleterre, de la grande Russie, vous ne souillerez point vos armes triomnhantes ni vos drapeaux dans le sang des innocents. Vous n'êtes pas des bandits et c'est en braves gens, sans peur et sans tache que vous irez à Berlin et à Vienne pour v prononcer la déchéance dés empires ie H\"henrollern et de Habsbourg dans l'intérêt même de la civilisation, de la naix du mondp et nour mieux préparer les voîps à l'affranchissement social, aux Et»ts-TJnis d'Eurone. Ils resteront humains tous ceux qui se battent pour l'hnmanijé H. GHESQUIERg,\nPétrograd, 3 octobre. — (Communiqué jfficiel). Le 2 octobre, la bataille d'Au• lustoip s'est développée avec un acharne- ■ ient éxïrême. L'ennemi occupait une po rtion défensive au nord du lac Wigry et -Uaquait avec vigueur de .Rachki et de iorjimen sur la chaussée Lozdzee-Schip- .ichtci, la première division de cavalerie. Ce combat eut lieu à la nuit tombante,. Les escadrons allemands, refusant d'uc- epter les charges de la cavalerie russe, $e jetèrent en arrière et se débandèrent, avec dé forte pert.e$, entraînant avec eux leur infanterie de soutien. Eaigrod, Kalvaria et Mariampol ont été iccupés par nos troupes. Sur la rive gauche de la. Vishde, des ombats peu importants ont eu lieu dans a légion de Kielce. Dans les Karpalhes, nos troupes_ sonl lescendues dans la vallée de la rivière Yagy-Ag. Un détachement autrichien d Mikulince a été repoussé et a perdu des :anons et des mitrailleuses. , LE'COMBAT D 'OSSOVETZ A DURÉ 36 HEURES Pétrograd, i octobre. — On donne les dé tails suivants, sur le combat d'Ossovetz : Les Allemands, n'ayant aucune autre voie pour approcher de la forteresse, s'en gagèrent sur, la route de Graje-'o. Quand ils furent à une distance de 14 kilomètres, leur artillerie ne put s'aventurer plus •avant,' le tetrain devenant marécageux. Ayant ouvert de . là un bombardement acharné, l'ennemi lança en avant de l'in fanterie avec de nombreuses mitrailleuses qui s'approchèrent de la place forte à 6 kilomètres. Les. Russes firent alors une sortie et, profitant de voies que l'en nemi ignorait complètement, ils envelop pèrent. les. ,<leux ailes qui étaient ' persua dées qu'elles occupaient toutes les routes praticables et ne s'intéressèrent qu'à la forteresse. Lorsque le mouvement débor dant fut révélé, un combat furieux éclata dans des conditions très défavorables pour les Allemands. L'artillerie de forteresse les décimait sur la route ouverte, tandis que l'infanterie russe, par une fusillade infer nale, dévastait leurs ailes. Le combat du ra .36 heures et se termina par la débâcle des Allemands. Cette débâcle dégénéra bientôt en une déroute désordonnée sur la .route de Grajevo. Les Russes s'emparè rent de toute l'artillerie, embourbée.\nVARSOVIE ET LA REGION SONT HORS OE TOUT DANGER Pétrograd, 4 octobre. — Le gouverneur militaire de Varsovie et de la région a fait placarder un avis disant que, dans ces derniers temps, la population est agitée pa,r des bruits absurdes, relatifs à une occupation éventuelle -de la ville. / Sur l'ordre du commandant .d'armée,- il parte à la. connaissance,du public, que ..Var sovie et la région soM' eorninë àu .pijraVarit hors die tout danger d'une agression de l'ennemi.\nL'ACTION SERBO-MONTÉNÉGRINE\n■■Le grand journal de Moscou. Viedomosti , publie la lettre de Kropotlûno iu professeur Gustave Stelïen, à-laquelle nous-, avons, fait' allusion 1 dans notre, nu,- , méro d.'avant-hier. Voici la traduction des principaux passages : Vous voulez savoir mon opinion sur là guerre : la voici, brève et claire. „ - A l'heure actuelle, tout homme qui peut.. et veut faire quelque chose d'utile pour sali ver la civilisation européenne, pour coriti-\" nuor la lutte en faveur de l'Internationale ouvrière, ne peut et ne doit faire qu'une chose : aider à écraser l'ennemi de nos aspi rations les plus chères, ie militarisme prus sien et l'impérialisme allemand. , , ' Liebknecht et Bebel ont iutté avec cet ennemi en 1871, immédiatement , après ' 'a guerre franco-prussienne, en protestant - con tre l'annexion scélérate de l'Alsace et- de -M: Lorraine à l 'empire germanique contre 'a volonté nettement exprimée des populations de ces contrées. Ils ont prévu les cbnsé'què& ces de cet acte de brigandage qui contenait en germe..les nouvelles guerres inévitables 1 et qui marquait un arrêt du progrés et de la civilisation. A l'a.ile gauche de l'Internationale, un au tre homme lutta contre l'ennemi pi-ussien î ce fut le Russe Bàkounine- qui tenta de. sou-; j lover l'opinion publique européenne 'par, ses lettres prophétiques — Lettres à un Français> -- qu'il considérait comme son .testament po litique. ^ .V\"-' Pour défendre la France; a.mmiêdâatenieht après la chute de Napoléon-,HI,--:-àe'.-'-feya; : Jié;,... vieux Garibaldi et la dépêche : « ta sainte chemise rouge a débarqué à Marseille: » le tour de l'Europe en annonçant ia .vdlonM du lion italien de défendre la France contre l'invasion germanique. Mais ce n'est pas tout. Les partis motléréa et bourgeois de l'Europe «salière, tous les hommes à pensée-indépendante, protestèrent alors contre l 'écrasement ,<ie la France... L'Europe:a compris que-le triomphe militaire de l'Allemagne signifiait l'arrêt de toute: la civilisation représentée'. Dar la France et le' renoncement par l'Allemagne elle-même à l'idéal humain qui inspirait ses mèffieurs représentants. .Tout le monde sentait quà, c'était le triomphe de la force brutale et l'ahaissement général de la culture. Et voilà quei cet Attila moderne lança,, sur l'Europe occidentale sa soldatesque bes tiale. Notre devoir est d'opposer à cette at taque tous les moyens à notre disposition.;. Les diplomates allemands suivent l'ensei gnement de Bismarck et, en même temps que leur campagne militaire; ils entament une campagne diplomatique, c'est-à dire uno campagne de faux et de mensonges. Kropotkine analyse les mensonges sans nombre de la diplomatie du kaiser, dès le début de la guerre. • Il termine sa déclaration sur les termes suivants : U faut souhaiter l'écrasement içoihpM'- et définitif de l 'Allemagne militaristes H- .nous f-st interdit 4$ rester .neutres* cur, ïâns le cas actuel, la neutralité , ne, seraii-, que .'.a complicité ^en faveur de leur poing, de- fer. Les alliés vaincront ; les droits des natio nalités a leur libre développement seront re connus : le principe féd-ératif trouvera, son application dans la carte nouvelle de l'Eu rope. Et l'unité des forces de combat èn;faca du danger commun portera ses; fruits. ;. La cause est juste : elle,triomphera, ! •.\nLES AUTRICHIENS REPOUSSES A ZW0RN1K Nisch, 3 octobre. — Sur le front Zwor- nik-Lezriltza, les troupes serbes ont re poussé plusieurs attaques violentes des Autrichiens, et leur ont infligé de grosses pertes., Les Autrichiens ont ouvert, de_puis hier, un .feu d'artillerie violent contre Chabatz et Xicliar. ' Sur tout le reste du front, on ne signale aucun fait important.. SERAJEVO COMPLETEMENT INVESTI Rome , 4 octobre. — On ; annonce de Saint-Jean-de-Medua que Serajevo est complètement mvesii. — ( L'Information.)\nSÏÏH MER\nPAS UN POUCE DE TERRAIS PERDU L'artillerie allemande diminue d'intensité\nLA'FLOTTE FRANÇAISE • DANS L'AORIAT34}UE Rome, 4 . octobre. — La flotte française de l'Adriatique a bombardé et détruit , la forteresse de Lustica, la formidable dé fense extérieure des bouches de Cattaro. (L'Information.) LES MINES DANS LA MER DU NORD Londres, 4 octobre. — Une dépÈche d'Os- tende au Lloyd, en date d'hier, annonce que le vapeur anglais Davdon, allant de Hull à Anvers, a heurté une mine la nuit dans la mer du Nord et a coulé. Neuf hom mes de l'équipage manquent ; les huit au tres ont été conduits à Ostende par une barque de pêche. D'autre part, on mande de Tynemouth au Lloyd : , Le. vapeur Tromo-de-Arendaï a heurté hier, à 6 h. 30 du matin; une mine et a coulé. Deux; hommes de l'équipage ont été noyés, les autres ont été sauvés Dar un vapeur de pèche qui les a débarqués à Nortshields. AVIATEURS ALLEMANDS SAUVÉS PAR UN BATEAU SUEDOIS Londres, 4 octobre. — Une dépêche de Copenhague au : Times, du 2 octobre, dit que le capitaine du vapeur suédois. Runa, allant de Gothembourg à Lybock, a sauvé deux aviateurs allemands qui étaient res tés 11 heures dans l'eau sur un hvdroplane avarié. UN DESTROYER ALLEMAND COULÉ PAR LES l'iIAPONAIS : ■ Pékin, 3 octobre. — On annonce qu'un dragueur de mines japonais a touché une torpille et a coulé. Un second a été endom magé; Il y a quatre morts, dix-neuf bles sés. • Les Japonais ont coulé un destroyer al lemand. UN CROISEUR ALLEMAND COULE UN PETROLIER San -Francisco, 3 octobre. — Une dépê che de Vo.lp.araiso dit que le croiseur alle mand Leipzig a coulé le pétrolier Elsinor, battant pavillon anglais, mais de nationa lité américaine, au large du Chili, le 15 septembre. u 4 1 H ♦ CE JOURNAL NE DOIT PAS ÊTRE CRIÉ\n• L'éta,t-major général • anglais a - publié ; un : nouveau communiqué dont le bureau de la presse -à Londres - vient de. donner connais* sance. U est très récent; et .par ; là-même :pàr» , ticulièrement intéressant. E» voici la traduc tion La description suivante a été donnée pat un témoin présent au quartier général an glais et communiquée par Ce bicreau de la presse : 29 septembre 1914. La situation générale, comme on peut la voir sur la carte, demeure pratiquetSient la même que celle décrite dans la dernière lettre, et la tâche de l'armée n'a pas chan gé -de but. C'est de se maintenir jusqu'à la reprise générale de l'offensive. Pas un pouce de terrain n'a été perdu et chaque contre-attaque a été repoussée, souvent avec de grosses pertes pour l'en nemi. -'v;';'-';.;\"--. ' GROSSES PERTES EN OFFICIERS Toutefois, la qui-stion de position est un côté seulement de lu bataille, et il y a un autre point, important à considére'r. Les récents efforts offensifs de l'enneiai ont éfô donnés sans cohésion et les assauts hvr -? par relativement peu de corps s ius iia; -.n avec leurs, voisins. Quelques-uns et . i un signe d'infériorité dans le cornmar, ; - ment, laissent trop voir les grosses periti en officiers qu'ils ont subies. De plus, l'artillerie ennemie .a - -dianau* d'intensité et semble atteinte ta di- : rection et sa surveillance. : La prenrièra cause est probablement due au transport de ma'iériel à d'autres points, mais.' !e<î deux autres peuvent être une conséquence de l'activité et de l 'intelligence dépioyca par nos aviateurs. Récemment, les Allemands s'étaient re posés sur les observations recueillies par des ballons captifs postés à l'arrière' da leur première ligne, méthode qui donne de bien pauvres résultats, en regard tifl ceux obtenus par les avions. Comme con séquence,, les dommages-que nous avons subis sont tout' à fait-'disproportionnés!'à l'importance des munitions -dépensées par l'ennemi. Vendredi 25, un calme relatif régnait dans , notre sphère d'action ; ' le seul iriei..- dent digrie,d'être : mentionné est,.le passage-- d'un aéroplane ennemi , à trav>'i\";. nos li gnes. Il volait très haut, ma;3 une, fus:: lf]de générale réussit à tuer sur le coup la piloté et à olesser seulement l'observateur. Ce dernier pan-int cependant à continue? lé vol pendant quelques milles, i? : ît enlit» forcé ,d ! 'a.tterrir, le pétrole lui manquant» et fut capturé par les Franç:.;?,. Cette nuit une attaque générale fut poussée contre la plus grande partie dés lignes alliées et elle fut renc :.;- 3 î e si3».,. dès le matin. L'ENNEMI EST PARTOUT 'OUSSÉ Les Allemands furent partf'-t repo i-A-o\navec de grosses pertes. Sur un des points\n","•âg EG3 positions, pj.r exemple, rn;.rch-î.st feû masse contre nous ils furent reçus pai cotre - artillerie composée de - mitrailleuse* i y i d'oeusiers, et on estirno çu'ils iaissèrezr E.GOO' tués- et -blessés. De . vains efforts furent encore tenté? ..'pour-nous repousser !g.samedi 28 à 8 heu rçs ; du, tnatjn x-t la .-même jour .l'après-irti ' ài ; l^rt'illéi'ié\" tira iàns\". discontinuer Le- Aîlemands. revinrent dan'ç une formatioi on T, plusieurs rangs épaule contre épau le. suivis presque immédiatement par un< '■colonne de soutien. Après quelques mmr ■.te? tous ces hommes Vêtaient confondu' tiîi une niasse offrant un excellent point d. cr.ir? à noire feu LES CANONS LOUFDS ALLEMANDS EN A6TSÛN Le dimanche 27. tandis que les canons '.ourds allemands étaient m action, on pou [■■ait entendre ieurs musiques jouer de? àymnes sacrés, probablement pour be ser vice Divin,. L'ennemi 3'a\\ança assez avant vers six heures du soir et, repoussé, re nouvela sa pointe vers onze heures, sans ?3us de succès que la nuit précédent?. Des pointes furent lancés toute la journée sui ■le. front. Lundi 28, il n'y eut rien autre qu'un bombardement assez prolongé et cette rlpmi-inactivHé continua le lendemain 29, sauf pour.la nuit où nous subîmes une at taque à notre extrême droite. Cn incident survenu ie dimanche 27 con tribuera à caractériser ie t\\pe du combat qui: ge livre depuis deux semaines sur de nombreux points de notre ligne. 11 montre ra , aussi l'extrême difficulté de discerner ce qui arrive au cours de rçiction et la nécessité de bons retranchements. A un sertain endroit de notre front, nos tran- .'bées avancées du Nord de l'Aide sont toutes proches d'un village situé sur le flanc d'une colline et aussi à une courte distance des travaux allemands, places sur déclivité tovmée par la \\allée 'de la rivière. L'après-midi était calme, ensoleillé, raais il , faisait une légère - baume §t, du point méridional, il était difficile de dis* ïirrruûT\" e aciement ce qui se r&ssait fur {'autre-rive. De temps en temps l'-eho du r-anon véveiî'?.it la vallée ev, de temps à autre, de différents côtés, le ciel était eclai- ré de ■ i'imprassioanante lueur des shrap- mells. 1 Tout-à -coup, sans que rie® l'eût annoncé, car il était impossible de distinguer le tir ries. lîo-witwfrs à cette distance, trois ou qua- î.-re shfapiiells tombèrent sur le village, en r-.ouleyant \"d'épais nuages de fumée et de poussière,, qui déroulaient lentement Leurs volutes gris-brun, .^pe.noter® côté, on ne répandit pas. $ien- tût, des coups de canon répétés éclatèrent au sorr/tnet de la vallée opposée à nos tran chées, c'est-à-dire .situes sur notre flanc. 1.1. -était impossible de localiser, par J$ 8.on. par la vue, cette canonnade. Prea- qu® en même temps, une succession ct'vclairs et de détonations, très sèches se remarqua, sur le flanc de la c-oiïîne, au bas de laquelle se mouvaient nos tranchées. -- -VIOLENT DUEL'D'ABTI'UUER'IE ■ Puis il y eut. un silence. Plusieurs colon nes de fumée s'elevèrent lentement et res tèrent comme figée, aussi régulièrement es pacées qu'une, rangée'de peupliers. De nou veau, les canons allemands à tir rapide Eiu/tipiièrent' leurs éclats, au loin, dans la vallée\" brumeuse, et, comme urf; écho, s'y ajoutaient les détonations des «jibus explo sifs ; les.nuages de fumée s'extravasaiçnt dans .l'espace, tandis que de nouveaux flo cons venaient augmenter leur longue file. Un autre silence, sauf de .vatgues bruits lointains-: Quelques minutes s'écoulèrent. Puis nos canons de campagne commencè rent à gronder de 1 a |.re coté- de la vallee, l'un ap^ès l'autre, dirigeant leur feu sur tes batteries allemandes avec une préci- sion c-poiss&rw-w-• ■\"Sis.?volî;es''ae\"'3u-ecédèrest, pwî# le silenca FepïitçAiirouWé Seulement pâT- ie brursse-- ment des s-hrapnells. On voyjilt les ^clairs- et les-flocons de fumée. ç'arrŒodiïr en rangs ■■ parfaitement réguliers : nous domptâmes un, ceux, trois, quatre, cinq., s£g, à me sure qu'un shraDtie.H éclatait, .-^v«ç une net teté délicate, au-dessus d'unei chtose indo- oise-qui avait l'apparence d'Upe ruine à l'oree d'un bois. Après un. bref intervalle, le *ca»on en* nemi tonna de nouveau, st la fumée 3'opaissit. Elle formait snçiinfonant un écran o'une immense longueur, i^u-dessus des tranchées. Nos canons répondirent. Et le duel contjmua pendant quelques temps. \"..VAIN-S-RESULTATS DE L'OFFENSIVE ALLiEMA^.ÛE Ne. sachant où nous étions,, et se cfoyant . eux-mêmes ignorés, les artilleurs' alle mands s'attaeria-iei-u- ià prendre nos trén- cnées en enfilade. S^liis doute, ils comp taient.-y arriver av-ea le temps, car^ avec Leur, gaspilli. ye accoutumé de munitions; Lis continuaient, à no.us arroser- d'ei |tJie »S4 -gescto.ss, qui sont une sorte de combinai son de shrapiiela et .«d'obus ordinaire p. De temps à autre, un projectile lancé à angle-très-ou vert sautait par-dessus la col- Unetet:.allait éclate/' dans le village. .11 n'y avasit alors rqu'à souhaiter que les nôtres se Jussent- bifjn terrées- dans les traiM&tées et tes villa.gsf lois daos leurs caves. Inform'ation prisse, nos hommes savaient pu se mettre- a l'abri. Les tranchées, dans t'a près», midi de ce. dimanche,-avaient», coin- - me-h^-tesi des-.sections des quatre bat-atilions angles, le Dorsch, 1e West Kenh, ie Owf.t Yorshire Lighî Infanity et le K^ng'n' Q-i/tfih Sco'lish Borderers, qui reçurent plus ifBO- projectiles-, et n'eurent que 9 ibles- Ve lendemain. 109 obus tomiièrant -.sur ÎP3 tranchées occupées par le Weat ftpnt àeqimenl seul\" R - ■ itat : 4 ofiîçiers pres que enterrés par les explosions, puis <Sé- ij- ï-j aucun mal ; un soldat éccjrcisé. .... Hait resté inoccupé.\nCHEZ LESJEUTRES A0U8. LE MAINTIEN STRIAT ' NSUT.îJALITê La Haye, 4 oçtobre. — L'n.c\" not' viôjn l'être publiée par la commission offlçielK iu conimerçe néerlandais. Cette note indique que la commission y :-u. connaissance de quelques cas. de pÇ> .onnes ou de maisons de couimèrce tVoi •lispoçées & fairès des -affaires conimerçî« es incompatibles avec la . neutralité di .•pyamnç et d^ nature à augmenter les dd içulîés déjè erçées à son commerce d'où ; rç-mer. l« commi^sicoci ajoute quaSu déviî®r. autant que possible, que çie t-çja'açt^s, hiPi q^s exceptionnels, p.v-sswi' donner matière à l'extension de l'étaî de srôge au grand centra. commercial hollandais de Rçtter dam. elle a examiné la po:>?îbU5té de pu blier les noms des né-gociaats ayant en freint la neutralité. On croit néanmoins que l'état de sera prochainement proclamé à Rotter dam, DES FAITS_DE GUERRE LE CAR M ET D'UN FANTASSIN BAVAROIS On a tromé sur un jeune fantassin ha- varois tué dans les tranchées un carnet de notes qui donne des renseignements sin cères^sur les effets de notre artillerie, l'ef iicacité de notre service d'afroplanes-éclai neui'3, et aussi l?s privations que le soldat allemand subit,. Ce journal, dont la censure militaire a supprime les dates, est cependant toyt ré cent, et tçut indique que la situation cri tique des Allemands ne s'est pas amé lioréa. ... septim%,-c. — A 9 heure?, nous sommes au. .combat, tj sTagit de prendre la village de .... Nous recevo®? un tel feu de l'artillerie française que bientôt -nos positions sojit-in- tenabî-es et.novts reculons. Nous nous çauvans avec Je drapeau, -Lç porte-drapeau a rççu une Wîe dans ia main; Le feu est trop intense. ... septembre. „ Dans l'obscurité nç-Us fai- sons .des tranchées de ijO centimètres sous '.e teu meurtrier d,o l'arallerie française. • La nôtre paraît trop faible. hs> matin; les aéros français noas esDionnent sans interruption. Pleins d'anxiéSf;, nous restons assis dans nos trancfiées. C'ese le jour de l'artillerie fran çaise. Celtes de (fcos troupes occupant le front du pont de... «Kit terriblement souffert. A côte de moi, d\"?^i groune de ICO hommjs, il en reste S3 i ... septembre. Dans les tranchées, nous sommes trempés jpsquîaus os. On s'y habi tuerait si les efïdavres des hommes ne sen taient pas si mauvais et si tes mouches ne se multipliaient paç. ... septemli-e. rsovs prenons notre unique repas à 20 heures, puis noua continuons ô marcher to.ute la nuit jusqu'au matin 8 heu ■; res. On nous raconte 'que ce n'est pas une retraite, mais b(ep un mouvement ; cela à toutes les apparences d'une fuite ! \"Nous nous arrêtons à quatre Kilomètres de Z... Sous avons toujours i^aim et noms n'avons absolu ment rien. Il ptaut à-torrents. Nous, creusons des tranchées et on ne nous laisse pas de repois. Il faut toujours remuer la terre. Subi tement, il arrive des. obus et ds? solirapnells qui nous forcent à reculer, car nos tranchées ne sont pas terminées et tout ,1e corps d'ar mée doit s'enfuir. A 18 heures, voilà les. aéros français. ... 'septembre* — -L'attaque est extrêmement violente. Nous réglions collés homme à hom me, inondés par las obus de l'artillerie fran çaise. C'est un teïi d'enfer. Pendant toute la journée nous n'avons rien mangé. Le soir, on nous donne une ration. Elle rte tait tins plus d'effet qu'une goutte d'eau sur une pla* que brûlante. . Le correspondant du fîmes relate cer tains épisodes des combats qui se sont li vrés dans la région de Reims et entre au tres faits il signale le suivant qui ne man que pas d'imprévu ni d'originalité : Les derniers rapports semblent indiquer une retraite générale des îortes lignes de Qéiense qu'ils avaient construites au nord de 7,..., ainsi qu'à l'est et à l'ouest. D'après 'es descriptions, jeurs tranchées de ce cote sont de merveilleux travaux d'art. Profondes de deux métrés, -elles- sont en beaucoup da cas renforcées avec du ciment armé. Les tra vaux ont été exécutés par torca par des ci vils, alors que les Allemands étaient encore sur la Marne. . Jusqu'à cette ligne, les Français avaient avancé pas a pas, jusau'à ce cru'à certains ! points ils se soient trouvés a 75 mètrea des | -Allemands, Je crois que l 'état de ces tran- ciiées lorsqu'on pourra les examiner, sera lamentable. Des hommes ne peuvent pas vivre comme des rats pendant des semaines dans des trous non draines. La bataille a dure sans arrêt et les blessés comme 'es morts étaient obligés de rester où ils tom baient dans, la boue et l'humidité. La nuit des tranchées avancées, tes Fran çais pouvaient entendre tas lamentations. , O sont sans, doute ces considérations, au tant crue le fed des Français, qui ont délogé 1rs Allemands de leurs forts en miniature.\nLos Japonais [réparent l'ilssaut - DE TSING-TAO .\nroklo, 3 octobre, — Officiel. — A Tsing- Trv, un ai ru (do ne allemand a ter/lé deuz tus' .-l'attaquer les navires japonais, sans succès, l'n uén/ointie japonais a lancé des bom- (■■y iu\" un'ballon captif, que l'on remor- 'pn.it vers Tsing-fao. On ignore si le bal lon a été endommagé. t.ri fort.-, et des navires allemands bom- t'crrl^vi ccii itumment l'armée japonaise, ry.'i p.'/'(l'ire lentement s.on grand assaut contre Tsiug-Tao. LES -JAPONAIS S'EMPAfiENT DU OHEMIN DE FER DE OHAN-TOUNC fVf.-i??, A octobre. — Les Japonai-3 ge sont emp-ires du chemin de fer Ciu Chaa-Toun^, de Tsinan-Fou à Wei-Hsien. Les : .Chinois semblent opposés à cette impure, mais les .lanonais font remarquei qu'ù est stratégiquemenî impossible de prmettre aux Allemands de 'contrôler le n.ïcmm de Sur durant les opérations contre Xii-o-Tcbéou. Et ils rappellent le traité mo-.iliejimind de 1SW. qui accordait uiu i:':a r t? à l'Allemagne et qui prouve, di \"eoi-i!s. qu? io. compagnie de ce chemin d^ t°r est eî-sc itieUement aJ'emande.\n' EN ALB ANIE F/f\" , • , -tobre — Une dépêche d3 Val- .\"fta dnTj e que les Epirotes ont évacué Sêrat et Zoitraphes et. ajourné leur mar* ^ ':r V. iona. — CL'i/t/wmation.)\n■ TOMBÉS D'ANS .UN' PièaË Les communiqués officleis de ces der niers jours signalent des batailles achar nées. Voici des détails .sur-une des tentatives infructueuses des Allemands : Apres avoir pendant tout un. jour attendu} des \"renforts d'Alsace, les troupes allemandes s'avancèrent dans ïa direction de N..-. Hs vou laient tenter un- assaut décisii. Nos positions /■talent fortifiées. Dès sue l'ennemi fut si gnalé notre cavalerie s'était portée à sa ren contre, occucant le villa® de N... Il fallait ensuite qu'après une légère résistance elle évacuât lë pays et attirât par une retraite ff-inte Ks ennemis vers le bois de L... C'est là qu 'étaient massés no3 soldats et auatre batteries de 75. L 'opération se passa mathé matiquement. Après Quelques coups de feu, nos eavahers quittèrent le village. La garde prussienne -r- toiiiour-3 elle r- crut bon de. s'avancer, précé dée des hussards de la Mort. Les Allemands criaient : « -Vonvaerts ! Vorwaerts ! » et, pendant trois kilomètres, poursuivirent les nôtres. Le piège était Và. - , Brusquement, l'ennemi n'eïanî DH'.s ou a cinq cents mètres de L..., la mitraille iailhî du bois Les taillis silencieux crachèrent 8 rhort. Ecrasés Sous upe avalapcne d'obus, le* Ulemands fureni pi'i3 de panique et s'en- fîiSrent. nous laissant huit cents pr^onmers, parmi iesnueîs un colonel et ùja officiers. L'?»1R®8§IWE 01 NOS t« VITRIERS r . Un correspondant du Times qui a _pu parcourir touta ia r^ion qui avgisins Nancv raconte le bridant l'ait d'armes sui vant d'un bataillon de cha-?seur3 à pied : Dps soldats de ce bataillon avaient -été en tourés par les Allemands et invites à se rpïiiir^. 'D'ur-e seul» vois, .ils refusèrent. L'ordre fut alors donné d'ouvrir sur eus un feu de ' sa \\srès çhàque saîve, les survivants criaient 0 Vue la France ! » Finalement, à !i. suit? d 'un effort inexpliqué et Inouï, les £50 chas- ■vurs qui restaient, réussirent à- repousser rennenti et - reprirent fa position, laissant plus de t.000 Allemands morts sur le champ de bataille. EN AUTRICHE LES VICTOIRES RUSSES PROVOQUENT DES MANIFESTATIONS HOSTILES Perpignan^ à octobre, -i* Les journaux espagnols publient une dépêche de Renie dissrlt que--les nouvelles des défaites de l'année autrichienne et des victoires russes provoquent- des manifestations hostiles m Autriche. ' A Vienne; la fouis aurait lapic^ 1« u\\l' abÇ^e lie la guerre, —? {Havca j\nLa OorrËSpsiiifioe île iiss Soldats\nJ'ai .rsfu te h'itrp suivant?.'Je- sqis qys'fff} ravaille à améliorer. Le miniiird de la luerre communique même h' revultbt de es efforts, (\"est bien. Mais peut-être titre n est pas encore inutile. P. R, Mon cher Renaudel, Tu. sais, que je combine avçe les occupa- ions d'un bon soldat dç 2 e ' classe, '■ ç'èïies . i'un secrétaire supplémentaire d'une com- >agnie d'un de nos dépôts d'action. 4a puis te dono^î\" '« Ç® titre qu^Iq3,îss •enseignements sûrs, vécus, de la çprres- ..joadanee mîataire, .qui îi®nî tant au cce^r de toîw. »■ 8. « c>4{, avaot tout; i® qu'il îaut jhan^r. Il est o^uîe de presqu® tçtu? les ï»ut le monde b sait. Ce -ront, acme.Ue- nent, t«s dépôts qui reçgivent -les lettres •t les iéexpéaicnt, do ia France vers l'tir- née. Or, voici cç qui se produit : D'abord les vaguemestres des déoôts -ont, pour la plupart, incompétents (nma- aère postale et n'ont pas su organiser eurs bureaux (certaines lettres mettant •ouwiit [ lu&ietiïs iours a en sortir. Ajoute à cela que le personnel que l'ad- udanî-ctKî a i-.ctuii ses ordres est aussi in ompétent que jui et que, pour s'enibua- uer en plus grand nombre et plus solide ment, il ralentit la besogne- plus qu'il ne expédie. Ensuite, le bureau da major est orga nisé de telle façon qu'il est presque impos able de tenir un registre d'adresses s v jour t facile à consulter. Dans l'immense pa- lerasserie militaire qui nous submerge on l'a pas réusai à établir des list?s exactes les diverses formations qu'ont fournies let O.Of.tO hommes qui ont j.aasé par les deux égimçnts d'aethe, de t\\ serve, et, lc*3 dix ■Qtnpagnles. de dépôt. Songe qu'açtueAle- nenr il nous rentra déjft, de3 évacués des létachements que nous avons envoyés au début de septembre, Le bureau du major a donc rençjacé & •éespédier- les lett res lui-môme. - il n'a que ses contrôles par compagnie, et '1 distri bue les lettres aux compagnies de dépôt. C'est, è, celles-ci de trouver, à qtielle for mation l'homme a été affecté, ou à retrou ver l'homme s'il est encore présent ou déjà de retour. Or bien peu nombreuses sont ! es compagnies qui ont eu !o personnel né- ■e^-saire pour établir les vèpertoîre.3 Réces-' saires. Supposons cependant la lettre expédiée enfin. Elle a encore bien peu de chance d'arriver au front, sur la ligne de feu. £Uc ne parvient guère qu'aux officiers, et en core. Elle ne leur arrive guère qua dans 'e cas de leur rassemblemenî ou do leur Jaulonnemcru. Mais eus hommes. Eu-< i -estent toujours perdus, isolés dans leurs ; compagnies, ignorant même quelquefois ce qui.se passe dans-la section d'à-côtéi Au* nommes, aux 3.000 hommes du régiment J 'e vaguemestre et ses deux, secrétaires nr peuvent distribuer l'énorme pitance de let très que nos courageuse^ familles leur en voint. Il n'y a pas d'ordre possible, de poste possible dans un régiment qui se- bat. îî faut attendre que le régiment soit remis en seconde ligne, ou au moins en réserve, pour qu'une maigre manne de let tres puisse tomber. Mais !ù encore ce sont des lettre-! 6par ses, celles de- quelques courriers qui peu vent seules parvenir. Le régiment- n'est pas suffisamment - bien informé pour ■-savoir exactement où sont et quels sont tuus les hommes de toutes les compagnies. Le? compagnies scuh's ont des états à peu prè« à joui, et aux bureaux du- colonel • on fa'est pas outillé pour les transmet^ au .vagues mestre et aux adjudants de bataillon, ni pour faire suivre aux blessés et malades. A Ce qu il faudrait c'est que îe service fût organisé dans las corps eus-mfimes et pa les postiers eux-mêmes. Pourquoi ne pas adjoindre quelques ambulants éprouvés, et quelques facteurs à chaque unité, dépôt régiment d'activé, régiment de réserve \" Ils auront tôt fait de préparer des -systè mes de cases et de fiches,, analogues à cel les des bureaux restants ; ils auront tô fait d'installer des bureaux ambulants et des bureaux de tri. Et puis ils .se chargeront de la distribu tion ! Quelques braves facteurs, un bor Lebel en bandoulière, des cartouches dans leurs cartouchières., iront volontiers fair? les tranchées et jusqu'aux plus petits pos tes. Et on mPmc temps que in viande fraîche qu'on n'a guère souvent le temps de cube et de la boule qui n'arrive pas toujours, nos camarades recevront la nourriture de leur cœur, des nouvelles de. ceux, pour les quels ils se battent en héros. Poursuis ta campagne, mon cher Re naudel. Elle aboutira. L'armée a le pou voir de réaliser le vœu unanime des sol dat 1 ? et du pays, elle n'a qu'a faire apoa? à la compétence de : quelques milliers de oostiers qu'il lui suffit de militariser.\nlia Vie â Paris\n: & S- »\nta! l'tri œ te Frltsiisfs iitl® A GENÈVE Genè f., octobre, -w (fie wt?e cor respondant .particulier.) — Depuis les pre miers jours de septembre, l'Agence m.s prisovirierti dt' guerre îonctionne dans notre ville. Elle est dirigée par le Comité international de la Croix-Rouge. Chargée d'établir des relations e p lr 2, '- ô3 prison niers de guerre et leurs familles, _-çll^. ts* çoit chaque jour des milliers de lettres, de cartes, de dépêches. Uns cinquantaine de volontaires travaillent à dépouiller , ce courrier immense, qui va Rallongeant sur de' longues tables. Confédérés de la Suisse allemande, Alsaciens, Hollandais, poly glottes tous, ils correspondent. avec les comités locaux de la Crois-Rouge qui peu vent atteindre les prisonniers. Cette œuvre est un admirable complé ment de la Convention de Genève. Des femmes du peuple, des fiancées, de.s amis, M-. Beleassé, inquiet pour son fils ; M, Edward Grey, oui cherche son neveu ; le recteur de l'université de Munich, M. von Mayr» vice-président du Comité inter national des Sciences sociales, dont le fils est en Angleterre, tous les rang3, toutes les situations sociales, tous les : titres sont confondus dans la commune souffrance. ^ j.'S. ■\nContre les fausses nouvelles UNE INSTRUCTION EST OUVERTE ' A la suite de l'enquête qu'il avait ordon née, le gouverneur militaire de Paris a de- j:dé qu'une information judiciaire serau ouverte pour délits d<3 fausses nouvelles, d$ feus et Uaggs -4e. les eaip de la Djiûs UNE ENQUETE OFFtCB&LL! - Q»: aaH. qus l'arwée ^U«jp«Q(ji9» avant sçi. déîai,t(?. sur la .wa^-ne, a occupé la ré gion d? CMteau T liuerry à, .Uçatmirai 1 , c ç.st-à-d.U'f la régldn r; \"des sçur:es de ia -Wftiais, dont i©s eaux sont au nombre de celles qui servçjjit a aUmentçr Parts en eau petablç. Les Allemands mirent eç dé charge i aqueduc de la Dhuis pour leur commodité' personnelle ; ils fracturèrent les portes ds l'aqueduc et aussi celles du bâhmcnr qui protégé la source mfcine. D'autre part, à là suite des combats qui ont çu Heu dans ie périmètre do protec tion do la Dhuis, les victimes ont inhu méos >:ur piur a . Do nombreux c'idavre.i de chevaux y ont été également enterrés, Pour toutes re3 raisons, il a paru impos sible de remettre en service l'aqueduc de la Dhuis. L'alimentation de Pari3 en pau potable est, d'ailleurs, actuellement assu rée sans difiiculié par les autres dériva tions de la Va une, du Loin g et de l'Avn et pay. les eau* filtrées et . stérilisées er cas de besoin. Le préfet de la Seine a tenu cependant à.se rendre compte par lui-même de if situation de la région des sources de 1; Dhuis. Il s'y est rendu, aujourd'hui. ave< M. le docteur Thierry, chef du service d< 'a surveillance des sources, et 11 a pres crit toutes las mesures utiles, soit poui éviter ia contaminaiion de la nappe sou teyrainç, soit pour assurer le aettojage et ta, stérilisation de l'aqueduc. les réfugiés POUR -FACILITER LES .RECHERCHES' Un bureau de renseignements a été crét- à Lyon pour faciliter la recherche des Beiges et des Français que l'invasion a obliges a abandonner leurs ■ foyora. te bureau fonc- doiiiifl sous le patronage d-e M. Herriot. niajpe de Lyon,. sénateur du Rhône,, ot dp M. Mulatier, consul de ù Lyon, il invite ceux des réfugiés qui peuvent croire que <ies parents ou -des amis les recherchent 4 .lui faii« connaître leur adresse présente Toutes comipunipations doivent être adres sées au bureau de renseignements pour 'es réfugiés., à Lyon, hôtel de ta Mutualité, place Has^all, • ■Dr ers LE POiT DES INSIGNES- QË LA OROIX.ROUGE La préfecture cîe police communique ta note suivante : - « Dés personnes étrangères à tout® orga nisation sanitaire circuient en tenue d'am- uulaneière, avec des insignes de la Çro.ix- aouge, et. pénètrent dans les gares, et sur les ï uni -3 au moment du oassage des trains mi litaires.\nde ciucisses aux\n« Le préfet de poiiee. vient de rappeler les disposition? qui limitent le droit de porter c<rs insignes et d'jnviter le personne? de in ooîics municipale à rép^tner toute--usurpa- ! ion de ouajites. <■ On devra exiger notamment à l'entrée des gares la présentation de la carte d-'idan, titô avec photographie délivre® par l'admi nistration- d® la guerre ou par une des asso; 'iations reconnues françaises ou étrangère: et portant le timbra <iiU - ministère de in uuene ou du service de santé d.u.,aouv.ei-ne- ment.militaire..de Paris. ■ Offre? et CE ivfes fiaiica^ièf'es Le Comité central ordt'nnù^, fondé au P. n - lais-Royal, galerie d'Orléans, Office colonial, sous-les auspices-rie la représentation ardon naise, prévient ses-compatriotes ou'un bulle tin périodique, le Bulletin Arâennais, conte nant de nombreux r-onseigneroents leg con- \"ernanî, -sera, mis en vente dans la plupart les gares du centre et de l'ouest, ainsi qu 1 '- l'rovi 'P. Dijon et Lyon a partir de dimanch, 4 octobre. — La Fédération des sociétés altaciçnnes lorraines de France et des colonies a déjà •eçu de l'argent de nombreux souscripteur? ■iont les noms seront publiés dans le journal ! i Revendication. ■ . Elle en demande encore afin d'être à même de poursuivra l'œuvre si nécessaire d'aide et d'assistance qu'elle remplit chaque jour au orofit des nombreux Alsaciens et Lorrainf lue la guerre a réduits au plus extrême dé nuement. Le comité rappelle que les fonds souscrits sont recueillis et-les .secours distribués par son vice-président, M. VuiUaume, oui se tient torns les jours a la Gazette du Palais, boule vard du Palais, D, à trois heures.\nUS L! PARTI ET LES STIBIMTS LE8 REPAS POPULAIRES La solidarité' sûfiiallsîÈ. et ouvrière du XS V 0 arrondissement. Puissent .les lignes que nous écrivons sur ^'.organisation des soupes communistes et de repas populairc -3 tomber sous Se? yeux, des ouvriers et des socialistes de Paris aux prises avec le sauvage enva hisseur I Elles leur apprendront\" que les camarades, des syndicats et des section? du Parti sont, .eux aussi,, à l'œuvre pour atténuer }es répercussions de î horribit •fléau qui désole notre pays, qu'ils dé pansent sans compter l^ur temps r-t loui peipe pour subv&nir aux besoins des fa milles des travailleurs qui forment l'im mense majorité de notr'.i armée. Et les travailleurs, après avoir lu nos petits bul letins de bataille contre la misire et U chômage, auront le cœur plus ferme çt le courage plus viril. Au XIV» arrondissement, la section so cialiste et les syndicats ont obtenu de mer veilleux résultats dans leur organisation des repas populaire, sous ls.<? auspices e* avec le contrôle de ia municipalité qui m* rite, elle aussi, les plus granas éiogçs. C'est au 23 de la rue d'AJésia, dans le? amples locaux d'une ancienne fabrique d'eau de BelU, que l'organisation d'ali mentation populaire de la XIV S section de la Seine, est installée. Iles dëtsilid A J'hc-ure présente on y distribue KO re- ■pçs par -jour en moyanne, des repas com plets, un demi-litre de botnllon, une por tion de bceuf, use portion de légumes, une demi-livro de pain par personno. De temps à autre le menu varie, s'agrémente d'un\nragoqt au* pommes, choux. Comme partout, dans no? œuvres sem blables, chaque repas coûta vingt centimes. La section joint les dsux bouts sans trop de peine. Et même il est possible qu'elle économise un peu, parce que !e personne, qui acheté les marchandises et pn-nare les» repas, donne tout son. travail gratuitement Presque tous les repas sont empois a dçïnicile. Une soixantaine sont pris\" sur place, à des tables d'une propreté irrépro- çhable, H v a da«$ le.gr^nd et clair r^ec- toife une atmosphère de fraternité, pt'oe- peadant, malgré la staieté d'un tiède soleil d'arrièrç-saiaon qui s'épanouit i^i-haut. dans un ciel d'un bleu tendre.,, et pénétre par les croi,?éfs> on mange vite, vite et l'on cause à peine. La sourde inquiétude qui hante les cerveaux se réflète dans là mé- io.ncoiie des regawis. Nous avons complimenté i: municipalité pour son aide généreuse. Donnons aussi deux mots de juste éloge à M. Maisy qui a offert le local, aux commerçants du Soldat laboureur et des Llégants qui ont offert la verrerie, aux citoyens Tréîaut et Charpentier qui vont- installer gratuite ment un hangar pour ahriter la clientèle contre les intempéries des jours noirs qui vont venir. Et que dire da camarades qui sont à la tête.de cette œuvre de solidarité ? Us ■ions ont-expressément défendu de donner Leurs noms. Ils ne font que leur devoir tout simplement. Paroles de militants Sgus l'impulsion du même esprit, dc -3 ef forts semblables ont produit d'aussi beaux résultats, dans lo même arrondissement au 111 de la rue du Château, ù la Maison Commune où d'autres r#pas populaires fonctionnent sous la direction, des cama rades des syndicats. Pour le mf-me pris do vingt centimes, on y distribue trois cents repas ie matin, autant le soir, des repas simples, mais substantiels et satoureus. pès_ les pfemiors jours, l'œuvre a été parfaite. L'organisme des soupes commu nistes, créé pour les jours de grève, n'a eu qu'à se rem^tre en train pour l'œuvre; de solidarité issue de la guerre. On avait st-us ia main tout ie matériel et un per sonnel de vieux militants expérimentés. Oui, bien sûr. nous dit ie camarade du oâument qui .dirige l'œuvre et nous Interdit la 1® nommer-.nous rrendo&3 ici de grands services aux taxnilles des «• copains a qui ion? partis, aux chômeurs qui. demeurent\" Quand, ceux qui sont ià-bfis, à la grande iouarancs. a la grande peine reviendront — ceua; qui reviendront -r- pour reprendre l'outil- de travail;-ils verront que pçus aussi, nous avons fait notre devoir. - «Srftce à notre .œuvre,, les .«amlfles peuvent éconbmiser sur le montant de l'allocation \"ou des secours de ohômare de ouoi acheter un las de petites choses fiécgssaires dans un roé» na>i>.s. ' fclles n'ont pas faim. Iî ne faut pas, non nîU3, qu'elies^aient îroid. Il leur faudra du :harbon. Nou3 leur donnerons, du charbon. Ce qui m'attriste, c'est de songer que dans juelque^ communes, de la banlieue, à Cla- tiart et à Malakof par exemple les muni- 'ipaUt.es ne font -pas ce Qu'elles doivent M- •e Battez donc un pen de ce côté-là-le rap- >el .«las bonnes volontés. C'est nécessaire. On nous cite, avant qvo r.ous ne pre nions congé, dos commerçants du quar tier qui apportent ù l'œuvre commune leur lide per&onnellc. M. Clairet, avenue du Maine, qui donne de la viande, le. proprié» lire du\" Bazar de l'Industrie qui a donné du matériel. Un. ouvrier, le citoyen Hen- nel, donne cinq francs pftr semaine, un Russe deux- louis -par mois. C'est la bon exemple. — A.-M. M. :\nDans la Banlieue ON ARRETE DES ESPIONS\nTERRIBLE ACCIDENT EN GARE Un grave accident s'est produit hier ma tin en gare de Jouy-en-Josas. Une jeune fille, Mlle Mathilde Bruneau, jui s'empressait auprès des blessés, re- .-ueillant les lettres qu'ils adressaient à eurs familles, a été surprise par un autre train et tuée sur le coup. J.' .J» ... .. . i.,; , , , , ,,, • alitaliiiàsEMfiirsaïiaiis\n. Un de nos lecteurs, le citoyen L. C..:, qui habite à Villiers-sur-Mame, chemin des Lioi.n&s, nous écrit la lettre \"suivante : En chômage depuis le 2 août, j'ai vécu tout ce mois-ci, ma tenune et -moi,- avec ie salaire dune semaine, j'ai fait depuis lors .u-ut te possible pour trouver uu tiavail. Pet lias ■ perdues 1 A uout us -ressources, j'ai- trois foi» solli cité use secours de chômage- - à la mairie de Villiersrsur-iVianîe. ç>a ma reunudu- j'en i-ecevrajs. comme d'autres, quand la ville au rait de l'argent. ■ • - • • uaa dém«.rcne- auprès- de la .préfecture a été mutu-e. - J'ai eu Heureusement l'aubame d'une pièce da ;iQ .francs qu'un, ami compatissant m'a prêtés. Et j'ai pajssé le mois de cjeptoxnbi-e avec cens somme. 'Et maintenant c'est la ■misère-noire. Ojs dit qu'à Paria -.tersonne ne sauffre. Mais ici î îse sommes-nous donc pas dignes de la aolUcitude de la démocratie î Je euis mobilisable, - jïecté ■ à l'élément de défense de Paris. iVîais '\"attends im ordre spécial. Ah ! pu'll / vienne vlt.6, cet crdie i Je serai a.l'abri de la faim et, ma pauvre femme sera nourrie.\nLES PRISONNIERS DE GUERRE On communique, la note suivante : M- Gabriel Hanotaux informe las familles du chef de bataillon ftéal, du capitaine ds 'a Comtouç,. du . lieutenant'- Emile Boussus, que ces officiers ont -été • blessés, ''qu'ils sont pri sonniers à Halle-sur-Saale avec son txls- «1 pourrait-, par celui-ci,, faire parvenir nouvel les et argent au besoin. ' \"\nLes colis porfaux Bordeaux, 4 octobre. — Le service des coïts postaux qui avait dû être comp.o- .e.nent interrompu par suite des opera- aons de la œob.iisat.oft a été repris aer- iièrement en trafic intérieur de cnacun ies t'éseaux (Est, Nom et Ouett-Etat êx- •.:eptés). .M. Tnomson vient de s'entendre avec- le ninistre de la guerre, de qui relève dans >a situation actuelle le service des trans- jorts par chemin de fer, en vue d'une nou velle extension du service de! coiis n os* taux. ■ ■ ■ ■ . * A partir du 5 octobre, les colis, .postaux pourront être échangé.? en commun entra les reseaux de l'Etat, de l'ôuest-ltat, 4e l'Orléans, du Midi et du P. L. M; ïsaat queîouea exceptions en ce qui concerne ca dernier réseau), de même qu'avec la Corse, l'Algérie et la Tunisie, et dans les rela tions internationales avec les pavs qui sont h. lueme de coopérer r<service. La liste de ces pays peut être consultée dans les gares et las bureaux de ville des Cota» pa.gnjes de chemin de fer. les récoltes \" n<,ïd<avr, i octobre. — Le Moni'ci? Agricole de Bordeaux a demandé à M. Berthault, directeur de l'agriculture au mi nistère de l'agriculture, son opinion sur la production probable de la France. M. Berthault a déclaré que 1-e rendement des récoltas a été meilleur qu'on l'avait -uppoaé. Qn estime la récolte entre tiO cl ci, millions de quintaux. Les besoins de la consommation. et de l'industrie s'élevant à t» millions et les quantités nécessaires aux- semences à, 10 mil-lions de quintaux, il nous manquerait donc environ 13 millions pour faire face & tous nos besoins. Mais, a d'-. çjaré AJ. Berfhault, mantenant que les' droits da douane ont été supprimés, i' est à craindre que le-commerce importe trop, Ç-® qui pourrait cansgr une dépression dm cours préjudiciable aux intérêts de l'agri, culture. Î1 y a là un coint de vue sur le- quel je me propose d'attirer l'attentica au ministre de l'ctrricultur«. • Tué par «ne sen inelle Bordeaux, 4 octobre, —— taier noir, tin chauffeur d'automobile, qui faisait \" un'ë promenade avec deux amis dans une voi ture appartenant à son patron et qui n e- \\ ait ni sauf-conduit,, ni n'èce d'identité a été tué sur-le quai de.s Cliantiers de la Gi ronde par une sentinelle qui lui avait don. né l'ordre de s'arrêter et qu'il avait refusé d'écouter pour éviter, les eonséauences do son équipée.\nVIE SOCIALE\nCOMMUNICATIONS SYN DICATS BOURSE DU TRAVAIL DE ■ PARIS : La Commission administrative de lu Bourse ou Travail informe que *e 'rppv, «crétaue adjoint du Synaiwtt du Bilou, <4 meymio de- la Commission adminiscrativf!,' soldat au 153° d-j ligne, a été g i-vsme'ii blesse. Notre camarade est en tràitemént\"i 1 hôpital ce la Pitié, à Paris. Pour la Commission administrative • Pua des secrétan ès : Paradis. AU SYNDICAT DkS TERRASSIERS Le conseil d'administration du Svndicat u2.ns .£îi Soâîioff du ^ octobre, et' d-tii'id-y s \\ QT a soment de^ççt!$aliQ!5s, r ati.Tj de pe-rmet-ti-e -àus • cjuj -îravai^ru et en U.urs QOt.toPAiojis,^.'pa\\ et ' t }îi&^L i? 'Hi3''pr-C'nii&?' aout 3 dtatô de la mobtiisî'.do'Q cenéi^'Ie Lô Conseil compte &.:r ia- vigilahee ûc-s ir^. t&urs. d«;; VUuTïi'iulîe et û > q la u, s pour aver ti * les camarades c-o leur ent< u Dge d 1 c-?'-? n-écision f?ui a.-^te pris*?.: après 1 g ÉU'srid bre de réclamations c'es Il est entendu que le Syndicat ns luv~ au- ciine adhésion penfUmt la durée des hosti? Utés.- .lo Conseil et par ordre : le secrétaire Hubert- M CONVOCATIONS HI'l'NlONii j * t ! I \\ Kli-3 . Fédé ation de ia Seîne COMMISSION EXECUTIVE Réunion, ce sou- à 18 heures .49, rue de Bre» tagne. Tous les camarades présents à Par.» sont priés d'être exacts. — Le Sscié-ariat. SYNDICATS : Pianos eî o^Stias, — Réunion de conseil & 8 heures oe l'après-midi. La quesuon du se- pours .^ujc camara îles chômeurs. Pau n-SOCIALI STE- 9® SEstîon. - t - A 6 tieuies, chez le citovcîn Erai'.l, i bis, cité Piga^e. Le cuOau'ge ef ,j -3 seecm.-s. - < 11-' ^estion, -r— Lr.-;. m-srnbrv-s de le 11° sr- A - Uon,-. réunis le 4 octobre., adressant air ci toyen Chausse, ainsi qu'a sa famille,- l-\"urs conuoléances, émues et qui renouvellent leur sympathie pour la perte ds son • fils Henri, mort ,à la hataille de Burry-au-Bac. — Le &->• crétaire : A. Henie. ' •■n\" Jesjnosse. -,,A 8 h. ce- soir,' n:s da 'VS- néral-Blaise, 9. Réorganisation de- la cal«e de secours. , 13* SeoSion. a huit feeures et demie, aa sdège, 94, boulevard Auguste.Blanqui. tou=a ♦ d'administration ; Lepas populaires. ■ fSi Nustier, — A ..30'-neurès,' chez isotiîîf, r-oa .Belloni, % : commission exerutive. OamKi d'entente cies Jeunc&sse socialistas «Se ia Seine. — A' 8 heures, 49, rue. de r *r£> tagne : Commission. • f»ré-Sajsn.as8*«aSs, — A 8 h. 30 .soir, rém^ca de la Commission exécutive. salle de la Der- ception, mairie du Pré. FLO j betub.es lebb famille Deiille Résiré à Saint-Laurent, par Saint- André-de-Gubzac (Gironde) deman-'e des nou velles de sa famille évacuée d'Haraucourt (Ardennes).\nPETITES ANNONCES Compagnie des Coiis agricoles, à Lutersao (Corrèae), envoi f°,. contre mandat 10 fr • 2 beaux poulets à rôtir, 1 sup. lapin 1 livra laxd, il œufs frais, î nrimes. ^'ettez-vou5 à 2 camarades et es.sayeE, vous serez contents. L'HUMANITE • eas composé en cumuiaadit» • psjT -une fquipe c Vn(3rmiéS. O - N t r»rn\\\\p.D. Min I I-LU XIIMIW. II. . ... . .HMl. . I ■ ' »■ llMl r'Ui ta, uu in, » iU, i u«î uli (-.rulb^aUt, V. Simart, imprimeur. \" 15 *°.\n•asm.\nBAHANIA Suralimentation intensive \" A 8\\SES PRINCIPALES DE FARiNE DE BANANE ET CACAO PURS 'Usines à Courbevoia {Smm) •\nPendant la période d'épreuves que nous traversons et pour contribuer efficacement à l'alimentation de Paria, la Compagnie continuera à vendre tous les jours, au prix de revient, an certain nombre ds ses boîtes « 3ANANIA « dont chacune est préparée pour 45 déjeunera. La. farine de bananes représenta un maximum do nutrition pour un minimum da travail physiologique, eî l'analyse donne un coefiiciant alimentaire quadruple au meilleur des autres, aliments connus. En Amérique, c'est par milliers qu«î des rapports à ce sujet ont été présentés au Sénat do Washington, si con cluants et autorisés que nous nous proposons de les réunir en un seul ouvrage, pour l'instruction do tous. Un témoignage antérieur et non moins précieux est fourni par l'explorateur Stanley, dont ia nom est inscrit dans !'H : itoire, par son inoubliable traversée de l'Afrique centrale. Dans son ouvra,zo intitulé « In darkest Africa », il déclare n<? d'Être nourri exclusivement que de farine ds bananes, pendant les six mois que dura l'expédition. Dans un autAî chapitre traitant, de ce fait, Stanley conclut que si l'Europe connaissait les propriétés nutiilives considé rables de la banane séchés, iî serait inutile d'avoir recours à d'autres\" aliments pour subsister : la consommaU uïj en serait universelle et sauverait l'existenc* 1 à des millions d individus, forts ou faibles, jeunes ou vieux. A&ttunMration e£. Bureaux, 47, rue de la Victoire de 9 heures à midi» et de 2 heures à 4 htures.\n"],"language":["French"],"identifier":["http://data.theeuropeanlibrary.org/BibliographicResource/3000114597017","http://www.theeuropeanlibrary.org/tel4/newspapers/issue/3000114597017","http://www.theeuropeanlibrary.org/tel4/newspapers/issue/fullscreen/3000114597017","http://gallica.bnf.fr/ark:/12148/bpt6k253967x/f1.thumbnail"]}