{"relation":["http://data.theeuropeanlibrary.org/Collection/a0599","Notice du catalogue : http://catalogue.bnf.fr/ark:/12148/cb327877302","Europeana Newspapers","http://data.theeuropeanlibrary.org/Collection/a0142"],"rights":["domaine public","public domain","http://creativecommons.org/publicdomain/mark/","This metadata record is licensed under: http://creativecommons.org/publicdomain/zero/1.0/"],"format":["[OCR confidence] 0,482107"],"date":["1914-12-02"],"type":["Newspaper Issue","texte","text","publication en série imprimée","printed serial","Text"],"creator":["Parti communiste français"],"publisher":["L'Humanité (Paris)","L'Humanité (Saint-Denis)"],"title":["L'Humanité"],"source":["Bibliothèque nationale de France","http://gallica.bnf.fr/ark:/12148/bpt6k2540258","Metadata aggregated by The European Library","Metadata provided by National Library of France "],"contributor":["Jaurès, Jean (1859-1914). Directeur de publication"],"description":["1914/12/02 (Numéro 3881).","fre\n            Latn"],"contentAsText":["■ ---©«mi® ANNIE. — N« 3881 , 6 Pages — S* ¥W SPÉCIAUX j ( Î ono ' bes ftQRESSE PARIS (2») : 142, Rua Montmartre adresse télégraphique: humanitê-pah» TÉLÉPHONE I GUTENBEflO } Q^ea QliBUfilTÉ ANNONCES m Rw MaafenwtM. U*\nMERCREDI 2 DECEMBRE 1911 © Pages — 5\" 1* tournai ('HUMANITÉ est vendu an SelêlqBB Olr.ll» ABONNEMENTS Sans frais dans tou» les Bureaux de Poste lAjr fiaoia 3M OU Ikois 18 fr. flfp. 4 50 t sa ter j 31 . 10 80 S 25 1 7» i 31 > 16 50 9 * 9 *\nSeine | t S«Jne-et-Oise ] parlementa Colonies Étranger Union costal®\nJOURNAL SOCIALISTE\nFondateur : JEAN JAURtuS\nKARL MARX\net\nLA FRANCE\nLa Canonnade continue\nA tï cours de leur offensive rageuse contre les hommes et les choses de la démocratie et du socialisme, les adver saires de nos idées devaient naturelle- ment s'efforcer d'atteindre le grand phi losophe et économiste auquel notre Parti doit les fondements mêmes de sa doc trine et de son action. Quelle bonne aubaine pour eux, si il la faveur de l'impopularité et du res sentiment populaire contre tout ce qui ssl allemand* ils pouvaient persuader in x travailleurs français que les ensei gnements du fondateur de « l'Interna tionale », de l'auteur du Manifeste com muniste et du « Capital ». que la mé thode qu'il a donnée au prolétariat uni* versel 'étaient des enseignements, une méthode spécifiquement « allemands », que son influence et sa doctrine étaient empreintes de haine ou tout au moins de peu de sympathie pour la France ! Ps n'y ont pas manqué. Jamais plus audacieuse falsification de la vérité his torique n'avait été tentée par des ad versaires sans scrupules. Dans l'ordre théorique, est-il besoin . d© rappeler quel hommage éclatant Marx a rendu à nos grands utopistes du début du XIX? siècle, jusqu'à quel point il a'reconnu ce que sa pensée devait à Saint-Simon et à Fourier, les égards qu'il eut pour Proudhon même lorsqu'il raillait impitoyablement ce qu'il y avait de petit bourgeois dans son idéologie ? Faut-il rappeler, à côté de cela, les sarcasmes dont il cribia dans son Ma nifeste Communiste les piteux essais des inventeurs du « /rai socialisme » ou « socialisme allemand », Karl Grun et Cie ? ■ Faut-il rappeler 'es pages immortelles qu'il a écrites à la gloire du peuple de Paris et de sa Commune, proclamant que « la mémoire de ses martyrs vivra com me en un sanctuaire dans le grand cœur de la classe ouvrière du monde entier »? Faut-il rappeler que dans sa vie pri vée, sur trois filles qu'il eut. les deux seules qu'il maria de son vivant furent données par lui à des « Français de France » — à des réfugiés de la Com mune Mais 11 y a plus et mieux. En 1870-71, fil-ors que la France subissait l'invasion nltemande, quelle \"ut donc l'attitude de se \"\"socialiste allemandr \"dortt l'esprit avait pleinement atteint la hauteur de vues de l'internationalisme intégral 7 Le soir du 4 septembre, Edouard Vaillant et Charles Longuet, en un bref télégramme, apprenaient à Marx la. proclamation de la République, la stu erre désormais menée sur le terrain de ïa Défense nationale et lui deman daient d'agir sur ses amis, en Alterna* gne. Le grand socialiste de Trêves n'avait pas besoin d'ailleurs au'on lui indiquât, son devoir. Au nom du Conseil général de l'Internationale, en son admirable manifeste du 9 septembre 1870, Marx | s'élevait contre les ambitions bismarc- kiennes : ~ 1 « Les patriotes tentons, écrivait-il.icroiieait- 11s réellement qu'en jetant la France dans les bras de la Russie, ils assurent la li berté e-t la paix de i Allemagne ? Si la for tune de ses armes,- l'arrogance ta WK»ès.. et l'intrigue dynastique conduisent l'Ail e- nvxgne à une spoliation du territoire français, alors il ne lpi restera de choix qu'entre\" deux partis : elle devra se l'aire à tout risque, mais directement, l'instru» ment de l'extension russe ou bien il lui 'audra se préparer de nouveau à une ?u«rre défensive... contre les races slaves «t latines coalisées, Ijes sympathies aautement affichées le Marx pour la France républicaine 1e se démentirent pas un seul instant ui cours de la terrible crise d'il y a quarante-quatre ans. Plus notre mal-,, aoureux pays était vaincu, foulé aux pieds par le vainqueur arrogant et jruel, plus l'auteur du « Capital » af firmait hautement ses sympathies cha leureuses pour lui. ■ Ses lettres au Dr Kuselman, publiées gn 1903, par la Neue Zeit, nous en ap portent le témoignage éclatant. C'est ainsi qu'il écrit le i3 décembre 1870 : ...Le système ées réquisitions, J'incendie : ' tîss-village, les fusillades des franea-ti- s i: relii^ylés prisas d'otag>p§ et autres réca- pifcuMiiMïs de la «\"terre de trente ans ex- :\";: : »^t:-riç4igxiatiqii générale-.. C'est vrai ment une idée dir>«- Hohenzollern que Je. faire crime H une nation de conti nue. 7 ii se défendre quand son armée p&r- mar:?.ïf,e comprend tout le monde. il ne farut pas chanter -victoire av-iî;t ie combat. La guerre peut encore prriii'lve une tournure très désagréable. On , ne «ïOîuptait pas sur la résistance héroïque i|e l'a-mée de la Loire... Ls i6 ,janvier 1871. c'était dans une ïctlEe publique aux Daily News qu'avec plus de netteté encore Karl Marx affir mai se3 sympathies françaises, dans cette presse anglaise alors presque tout entière indifférente ou hostile. Après avoir stigmatisé toute la poétique des vainqueurs, il concluait par ces fortes paroles : Lu Franc» — et sa cause est heureuse ment !aîn d'être désespérée — combat en ce moment non seulement pour son in- dépendance nationale, m».i8 oour la liber té (ie 4 Allemagne et de l'Europe. . Même lorsque la France semblait dé finitivement vaincue et que tout espoir paraissait interdit à ses plus optimistes : défenseurs, après la. signature de l'ar mistice du 14 février 18.71. le grand so cialiste allemand ne désespère pas en core d'elle. Il flétrit les capitulards et écrit à Kugelman : Malgré l'apparence du contraire la si tuation de la Prusse n'est rien moins quc> plaisant®. Que la France tienne bon ! :Py'«iîB uHIlss l'armls.tlee à réorganiser -i/is-.ée et dense enfin à la guerre un\nL'ASSASSINAT D'UN PAYS\nl?Iîicesîdîe des: Halles d'Ypres\nn e!» et le ^s or chaud ENGAGEMENT tourhe a l'avantage DES français 15 heures En Belgique, canonnade assez vive pen dant la journée du 3Q novembre ; aucune attaque de l'infanterie allemande. L'ennemi a continue a montrer une as sez grande activité au nosd d'Arras. Dans la région de l'Aisne, canonnade intermittente sur tout le front. En Argonne, les combats continuent sans modifier la situation. En Woëvre et dans les Vosges, rien à signaler, 23 heures En Belgique, l'infanterie allemande a essayé, sans succès, de sortir de ses tran chées au sud de Bixseiioate. Entre Bétiiune et Lens, a la suite d'une affaire assez chaude, nous avons enleve le château et ie parc de Vei'rnelles. En Argonne, nous avons avancé sensi blement dans le bois de ta Qrurie. Sur le reste du front, rien à Signaler. *:♦—-—■ ■; : ■ LA SITUATION 1. — Les plus récents communiqués nous font voir une recrudescence d'activi té allemande dans la région qui avoisme Arras. De là à annoncer que c'est à cet endroit précis des lignes alliées que les Allemands s 1 apprêtent à donner -leur prochain coup de bélier, il n'y a qu'un pas, et nombre de chroniqueurs et de critiques l'ont déjà franchi. A nous qui ( ne jouons pas au prophète et qui cher- \\ ; chons simplement à voir clair dans le j présent et l'immédiat, il nous suffit de mentionner qu'ils Vont franchi. D'autres chroniqueurs, cependant, continuent à affirmer que ïadversaire masse dans la région d'Y près (à l'est de cette ville, exactement) des farces consi dérables : cette affirmation n'est proba blement pas moins exacte que la pre mière. Quoi qu'il, en soit, la Belgique n'est toujours le théâtre que de canon nades assez vives, mais qui, n'étant ac compagnées ou suivies d'aucune attaque d'infanterie, ne sont que bruit et que fu mée. Derrière la ligne de l'Yser, les Aile• mandée, sont-ils retirés jusqu'à Bruges et la mer ? La rumeur en a couru ; nous l'avons enregistrée. Mais elle n'est pas encore confirmée par les faits. En somme, sur tout le front occiden tal, aucun changement caractérisé. Nous restons sur la défensive, nmis y reste rons sans broncher, jusqu'au jour ??> l'état-major responsable estimera qu'il convient de donner à l'action une forme différente, En attendant. nous sommes au 2 décembre, à la veille de la rentrée du Reichstag et l'empereur Guillaume ne tient vas le succès décisif qu'il pou vait se flatter naguère d'annoncer aux représentants de son peuple. 11. — Il ne le tient ni à l'ouest ni à l'est. A l'est, sur le front oriental, les communiqués russes sont toujours so bres de nouvelles : on se bat furieuse ment autour de Loviez (entre Lodz et Varsovie), ce qui signifie. bien que. la grande bataille est loin d'être terminée. Plus au sud, la retraite des■ Autrichiens est absolument confirmée. Aucun ren seignement nouveau, en ce qui touche l'investissement de Çracovie. mais on annonce qu'après un combat de dix jours, les troupes russes ont pu fran chir les passages des Karpathes et se trouvent maintenant en territoire hon grois.\nLes Forces allemandes comment sont composées les armées ennemies sur les fronts qgcio htal et oriental\nLES UALI.LS D'YPUES /IV.l.Vi' LE BOMBAIWCMEST\nUn Aep .rédacteurs de niumanué, bien con- : «.!,t (te nos lecteurs pour les-campagnes qu'il ç. menées dans notre journal contra les: re- 'quins du Parlevient et de la finance, nous adresse les notes suivantes. Notre camarade, qui fut l'année dernière taxe de trahison par des adversaires sans scrupules et accusé de vouloir saboter la mobilisation, se trouve à l'heure actuelle au front comme volontaire. 23 Novembre. Territorial, j'ai obtenu l'autorisation de partir dans un détachement, de l'ac- : tive et • depuis trois semaines je mène avec lui la dure vie des camps. Je voulais voir, je vois. Nous sommes au plus fort de la bataille, en cette ré gion d'Ypres où l'armée des hobereaux fait son effort suprême pour percer no tre ligne, qu'elle n'arrivera pas à trouer. Pauvre Belgique ! Pauvre héroïque petit pays ! Àh l comme nous tous j'ad mirais les Belges, mais, depuis que je suis au milieu d'eux, c'est de la vénéra tion qu'ils m'inspirent. Pas un pleur dans ces foyers dévastés, pas une plain te dans ces\" familles décimées et erran tes. Une confiance tranquille, une séré nité douce. Ils nous donneraient espoir s'il en était besoin. La taMsraî d'Ypres Le martyrologe de leurs villes vient de s'augmenter d'une unité. Quand vous recevrez cette lettre, vous connaîtrez de puis plusieurs jours l'incendie des Hal les d'Ypres. Je viens „d'y assister, fris sonnant d'horreur. Jamais ce spectacle tragique në sortira de mes souvenirs. .Plusieurs fois je l'avais traversée, la petite ville coquette aux maisons à pi gnons. Silencieuse et vidée de- ses habi tants.' elle conservait dans sa tristesse\nPOUR LES RÉFUGIÉS BELGES Nos amis du Comité d'action organisent pour les Réfugiés belges, dans les locaux de l'Utilité sociale, la. coopérative du bou levard Blanqui, un dortoir où on espère loger chaudement ©t confortablement 35 réfugiés. Ç'eslt un point de départ. Mais dès maintenant il faut draps, couvertures, traversins. Les lecteurs 4e l'Humanité ne peuvent-ils aider le Comité à cet égard. Déjà quelques dons ont été faits que nous avons feransïnis, mais il faut davantage. Que nos amis ■envoient ce qu'ils pourront, soit à nous-mêmes, .soiit à l'Utilité sociale.\nP- R.\nROYAL-POLOGNE\nLe journal Excelsior, sous le titre flam boyant ïloyal-Pologno, 5 e régiment de cui rassiers, nous conte ceci dans son numéro du 27 novembre : Les cuirassiers du Royal- Pologne, 5 e régi ment sont partis avec 1 enthousiasme calme de tous les soldats français La veille du dé part, leur colonel, « un cÇiic type », avait fait venir dans la caserne deux prêtres pour con fesser \"ceux qui voulaient s'en aller « avec une conscience tranquille , et p r ê'treâ n'ont terminé leur mission que quelques 1 mi-, nutes avant le départ. Vous qui comme nous tous, socialistes, êtes pour « l'Union sacrée », ne trouvez- vous pas, que, tout de même, il a un peu exagéré, le colonel ?\ncaractère vraiment révolutionnaire !... et le nouvel empire toorusso- germanique pourrait bien recevoir un baptême fort inattendu... Au moment où le fondateur du socia lisme moderne parlait en ces nobles termes de notre pays et de sa cause, le >rand écrivain anglais Carlyn l'»tcca blait de sarcasmes brutaux et de diatri bes iniques tandis . ae ses propres gju \"ernants réactionnaires et son Parle ment monarchiste la livraient sans dé fenso au démembrement. êh&W ■ LONfitiHt\npassagère cet aspect d'intimité char mante qu'offrent les vieilles cités fla mandes. .J'avais admiré ses façades sculptées, les fers forges de ses balcons. J'aimais son canal aux eaux croupissan tes semblable à ceux de Bruges, son en trée que des lions de pierre défendent et la place bordée par les Halles fameu ses. par l'hôtel de ville délicat, par l'im posante cathédrale. Quelques maisons étaient déjà tom bées. De loin en loin s'élevaient des rui nes fumantes. En face de' la cathédrale même, une « marmite » avait creusé' un trou, béant et abîmé de ses éclats la. sta tue de ce Vandenpereboom qu'une chan son chère aux socialistes belges a fait illustre jusque chez nous. Dans l'ensemble, la ville restait intac te et l'on se consolait égoïstement des désastres anonymes en songeant que la physionomie si pittoresque de la cité n'était pas altérée. Les Allemands sem blaient respecter les monuments. Une seule bombe avait percé Timmensie toit des Halles sans toucher aucun des écus- sons héraldiques revêtant le double ram pant, sans écorner aucune des mignon nes ogives da la façade basse. Les Bar bares paraissaient soucieux de ne pas renouveler leurs tristes exploits de. Lou- vain et l'on s'assurait avec joie que la Deutsehe Kultur n'exigerait pas un sa crifice nouveau. Depuis deux jours cependant le bom bardement avait repris avec violence. Des maisons de plus en plus nombreu ses s'effondraient:- La gare, spécialement visée, se transformait en un monceau de cendres. Les obus entrecroisaient en tous sens leurs sifflements agaçants et les rues centrales devenaient impossi bles. Nous avions, en traversant la ville, évité tout juste un arrosage abondant. La Catitédrais et les Halles en fes Brusquement, hier soir, le bruit se répandait dans les cantonnements su burbains que la cathédrale était en feu. L'incendie, en réalité, avait commencé vers 2 heures, mais il prenait dans l'om bre de la nuit des proportions sinistres.; Je n'étais pas de service. Une course au pas de gymnastique m'amena rapi dement sur les lieux. La cathédrale flambait en effet. Le toit brûlait par le milieu. Deux pignons éclatants appa raissaient dans une lueur aveuglante. Le vant d'est chassait la fumée vers Le porche que surmonte le clocher, cein turé d'échafaudages. L'abside, par mi racle, paraissait intacte. J'espérais encore que les Haltes de meuraient sauves. Hélas ! comme l'hô tel de ville, elles avaient précédé l'église dans la ruine. Lorscpae j'arri vai sur. la place, les quatre murs seuls tenaient debout, penchant tous quatre vers l'extérieur. Disparu le toit aux écussons prestigieux ! Les flammes s'élançaient des fenêtres gothiques. Un brasier formidable élevait vers le ciel des gerbes d'étincelles dans lesquelles se dressaient les restes du beffroi. I La tour centrale, lézardée, semblait\n... jié ; à. tomber, entraînant les débris doré de l'antique horloge et, léf cloches brillantes du carillon. Des quatre tourelles d'angle, deux lui saient, intactes, mais les deux autres attestaient qu'un obus égaré n'avait pas amené le désastre. L'une rasée à la base, l'autre coupée par le milieu, elles prouvaient la préméditation et mon traient qu'une volonté tenace avait di rigé sur les Halles des coups multipliés. Les danons allemands s'étaient tus, comme honteux. La pétarade des soli ves crépitantes remplaçait celle de l'ar tillerie. C'était horrible et magnifinue, ce lu mineux bûcher dans cette dentelle de pierre. Des ombres fantastiques cou raient au gré du vent dans le vieux monument qui fut l'âme de la ville. Les ■ hourgmesires, le3 échevins, tes marchands disparus semblaient reve nus en hâte pour arrêter dans leur dis parition les souvenirs d'antan. Le désarmeront par ta guerre Ah ! l'affreuse chose que la ™'ierre ! Aucune des scènes tragiques auxquelles j'assiste chaque jour, ni le défilé de ceux qui partent aux tranchées dans le vent et la neige, ni le passage ininter rompu des ambulances automobiles, ni le bruit de la fusillade nocturne, ni l'ouragan constant de l'artillerie lourde, rien ne m'a ému comme la ruine abo minable et stupide de ces pierres insen sibles en lesquelles se cristallisait un peu de l'esprit du passé. En rentrant à mon terrier par cette belle nuit glacée que In flambée des échafaudages de la cathédrale éclairait, je me sentais envahi d'une tristesse hor rible en même temps que d'une rage froide contre les brigands auteurs de- tant d'atrocités. Les flammèches volaient en tous sens. Ypres brûlait de tous côtés. Y près après Louvain, anrès Malines. après Termonde ! Pauvre Belgique, pauvre petit peuple de héros ! Si je puis ces ^ours-ci retrouver un moment, je vous conterai des traits de leur vail lance. Quelle réparation leur doit l'hu manité ! Nous leur ferons la vie paisible et 'v^me rru'ils aimenf dans une Europe débarrassée des féodaux et des 211er riers. Nous leur donnerons l'atmos phère libre ■ nécessaire au travail joveux. ' - Puisque nous n'avons pas ohtenu le désarmement dans la paix, nous l'au rons par la eu erre. C'est, pour cela ^ue nous nous battons. Quel socialiste disne de ce nom, en état de porter les armes, voudrait ne 10ns participer de tout son 1 crrnr. de toutes «s forces, à un com bat comme celui-là ?\nSOIXANTE-DEUXIEME LISTE\n[Nous rappelons à nos correspondants que les noms des morts et des u'essés ne peuvent être publiés qu'après que les familles ont été avisées. Nous ne pouvons insérer que si la famille est prévenue.] NOS MORTS Charles Laignier, instituteur, membre de la 14° section, sergent au 169® rég. d'inf. Auguste Mortel, de la 17 e section, tué le 13 novembre à Dixmude. Edouard Lacroix, soldat au 255 e rég. dt'inf., fils de notre ca,ma;rade, membre de la section des Mages (Gard). NOS BLESSES Marceau Radier, de- la section des Ma ges (Gard), en traitement au Havre. Eugène Regnav.ll, de la 17° section. Louis Camuzet, dit groupe de ViUepari- sis (S.-et-M.). Rat, de la. 14 e section, blessé à la cuisse. Charrier, retourné au feu ; Garrachan, Jean Bejin, Léon Borner, Bourneix, A. Béjin, Aug. Auraisseau. (Tous les sept membres du Syndical des cimentiers de Lyon). Faurette, du Syndicat des plombiers de Luon, retourné au feu. Lucien Tchanz,du Syndicat des plâtriers de Lyon. G. Noit-elle, secrétaire de la Fédération de Saône-et-Loire. bïessé dans le Nord, en traitement à Pontivy {Morbihan). ;—.... 1 ,< - 1.11 . ■»-»■•«» . 1 1 1.. . 1 La Sonféreiica de Gopeiaitis ajournée Le citoyen Stauning, le leader du Parti socialiste danois, annonce, par une dépê che adressée au citoyen Diibreuilh, que la Conférence internationale des socialistes des pays neutres, qui devait se tenir à Co penhague, au désbat de décembre,est ajour née au 17 janvier prochain\nFidèle à. sa méthode de bluff, le gouver nement allemand vient de faire savoir au monde qu'il a présentement en campagne 100 coups d'armée actifs ou de réserve. Pour donner à cette notification reten tissante une apparence de sérieux, il l'a présentée dans ia presse incidemment, en indiquant les adresses auxquelles devront être expédiés, à l'occasion des fêtes de Noël, les envois destinés aux soldats en campagne. Certains journaux français ou étrangers sont plus ou moins tombés dans le piège et se sont émus de ce chiffre. 11 convient donc de rectifier, ce qui est facile, cette information mensongère des tinée à impressionner Les neutres. La réalité est la suivante : Répartition des forces allemandes entre la France et ia Russie Les corps actifs engagés contre la Fran ce sont au nombre de 21 Les corps de réserve engagés contre la France sont au nombre de 22 Nous avons en outre en face de- nous 33 : brigades de laiijdwohr, soit 8 corps de l'ar mée territoriale. Le nombre toitaj des forces allemandes, active, réserve et territoriale qui opèrent sur le théâtre occidental représente donc 52 corps d'aimée- Les corps actifs engagés contre la Rus sie sont au nombre d® 4 les corjps de ré serve sont au nombre de 10 A ces 14 corps s'ajoutent\", d'une part, des brigaides de landwehr représentant en viron 7 corps d'armée, d'autre part l'ar mée austro-hongroise. Nous retrouvons donc, en totalisant, le chiffre de 25 i corps d'armée active et de 33 corps de réserve engagés par l'AUero.a- gne, tant contre la France que contre la Russie. Composition des armées allemandes Il est intéressant de compléter les ren seignements en indiquant la composition des armées allemandes. Contre la France opèrent les 4«, 6®, 2 e , l ra , 7°, 3 e , 5 e armées, plus 4 détachements d'armée. Én Belgique, la 4® armée, sous les or dres du duc de Wurtemberg, comprend une division de marine et 5 corps de ré serve. En Belgique également, mais se prolongeant jusqu'à Bapaume, la 6\" ar mée, commandée par le- kronprinz de Ba vière, comprend 5 coups d'activé et la va leur da 2 corps h de réserve. La 2 e armée, général von Bulow, au \" sud de la précé dente, comprend) 4 corps d'activé et 1 corps \\ -de réserve. La l rc armée, général von Kluck, comprend à la gauche de l'ar mée Builow, 3 corps d'activé et 2 corps \\ de réserve. La 7 a armée, général von Hee- ringen, entre La-on et Reims, compte \\ coups d'activé, 2 corps l de réserve et une brigade de land-wolir. La 3 e année, général von Eiden, dispose- de la valeur de 2 corps d'activé, 3 coiips i die râserve, 3 brigades de landwelir. Plus à l'Est, la 5 e armée (kronsprmz): comprend 2 corps d'activé, 2 corps | de réserve et 3 brigades Je laiidweihr.. Sur les côtes ue Meuse, le détachement d'aimée du général von Strantz compt-o 2 corpis d^activa et environ 1 corps | de réserve. Enfin, ' de la Moselle à la frontière suisse, on trouve la valeur d'un corps de réserve et de 10 brigades de landwehr. Face aux armées russes, l'Allemagne dispose de -quatre armées ou détachements d'armée dont la composition, qui a sou vent varié au cours des opérations, était il y a dix jours la suivante : La 8 e armée, général von Schubert, comprend 1 corps d'activé, 1 division de ré serve et la valeur de 2 corps de landwehr. Plus au sud, dans la région de Soldau- Thorn, 3 corps de réserve et la valeur de- 3 corps de landwehr. et une division de landstuem. Entre la VstuJe et la Warta, 3 corps d'activé, 3 corps et, demi de réserve. A la frontière .silésienne, 3 corps et demi de réserve, 2 corps de landwehr. Conclusion En résumé, l'Allemagne dispose actuel lement : 1° De 25 corps et demi d'activé,dont 21 et demi contre la France, 4 contre la Russie; 2° De 33 corps de réserve, dont 22 contre la France, ÎO et demi contre la Russie. On aboutit ainsi au chiffre total de 58. corps et demi, tant d'activé que de réserve, engagés par l'Allemagne sur les deux théâtres d'opérations et non point 100 comme l'a prétendu faussement le gouver nement allemand. Si l'on tient compte des éléments terri toriaux dont ne parlait pas la note offi cielle allemande (landwehr), on trouve huit corps de landwehr engagés contre là EVan,<\\o 7 r-nrTO de larulwfthr enlacés con-\nUN SOUVENIR DE 1870\nJe retrouve un document parisien de\" 1870, un carnet de membre de la Ligud ' de la défense à outrance. A cette époque, pendant le siège de- Paris, tout socialiste marqué déjà de l'empreinte communeuse était à la fois fervent révolutionnaire et patriote-'- exalté. Le comité central des vingt arrondis sements où se concentrait l'action so cialiste révolutionnaire et d'où eilo rayonnait sur tout Paris, pour l'étendra et fortifier, avait fondé la Ligue républi caine de. la défense à outrance, dont les carnets signés d'un délégué du comité . et du porteur étaient pour les adhé rents, — et tous les membres du Parti' étaient adhérents, — ce qu'est aujour- ' d'hui la carte du Parti. . 1 Voici les principaux articles des lila^ - iuts ;\nFrance, 7 corps de îandvfehr engagés con. tre la Russie, soit en tout, sur les deux théâtres, 30 divisions territoriales. — (Of ficiel.)\nLes ligueurs s'engagent, à défendre-ia Ré* publique et la Patrie par tous les moyens. Ils s'opposent à toute idée d'armistice et de traité de paix avec l'ennemi tant qu'il oc cupera Le territoire français. •'?* lis luttent pour la liberté du monde l'avènemant de la République universelle. lis prennent pour mots de railAenïeJït > La République ou la Mort 1 » Au nom de la solidarité, tous les ligueun se doivent mutuellement aide et protection, asile et fraternité dans toutes les cireoii» tances et dans tous les pays, , _ Les ligueurs doivant donner l'exemple d« -- toutes'les vertus civiques... J. Ils ont tenu parole, et le lendemain du jour où, malgré leurs efforts, Paris et la France étaient livrés . aux Prus siens, ils faisaient la Commune et sau vaient la République. On avait, pendant tout le siège, déjà préparé la répression versaillaise, exci tant contre eux, comme seule cause da ta continuation de la guerre, les trou pes découragées par la défaite et qui tes appelaient, qui appelaient les gar des nationaux « les outranciers ». Si dans leurs rangs se fût glissé un capitulard, il y eût risqué sa vie. Les capitulards étaient dans les rangs des partis de réaction et d'autant plus nom breux que ces partis étaient plus réao- tionnaires. Et quand tes députés de ces partis de réaction se réunirent dans l'assemblée de capitulation de Bordeaux, tes rares députés socialistes : Delescluze, Pyat, Tridon, Courbet, Razona en sortirent* protestant contre l'œuvre de trahison nationale et ne voulant pas rester au nrlieu des coupables de ce crime contre la patrie et la République. Non moins socialistes et aussi pa triotes que nos aînés de 1870 ; ayant conscience de résister à la plus odieuse des adressions des temps modernes, à la guerre offensive de l'impérialisme al lemand, ayant la volonté de le vaincre, de l'anéantir pour 1e salut de la -vitrie et de la République, pour la liberté des peuples, nous n'avons pas besoin, poui affirmer cette conscience et cette vo lonté de fonder une lis-ue qui n'eût fait que redire, sans y rien pouvoir ajou-- ter. l'idée, la passion, la volonté éner • gique et résolue, républicaine, socia liste et patriotique du Parti socialiste. ED. VAILLANT.\nLE ROI D'ANGLETERRE EN FRAN CE // vient visiter le quartier général de Farinée britanniqas Londres, 30 novembre. — Officiel. — Le roi George est parti hier soir pour la France afin d'y visiter le quartier général de l'armée britannique. Il était accompa gné de lord Stamfordiiam et du comman, dant Wigram, L'émotion à Londres Londres, 1 er décembre. — La nouvelle dn départ du roi pour visiter ses troupes sut le front a causé une grande émotion à Londres et dans tout le pays. Le roi trouvera un accueil enthousiaste auprès de ses soldats qui combattent dans les tranchées et qui ont pour lui un pro fond attachement. La présence du roi parmi ses généraux inspirera un nouveau courage à l'arméa anglaise. Dans tout le vaste empire britannique, la nouvelle de la visite royale sera reçue avec, un sentiment de vive satisfaction. — (Ha-- vas.) 4' * » if ' ♦ » ♦. i* 4\nCE JOURSAL NE ÛQ/T PAS ÊTRE CRIÉ «•♦«»«4 »4»4«4 - 4-4 >♦\nNOTES PRISES SUR LE FRONT I- .11 .1, I I |. | ,l«| lî ■ l| ■ ■' -I Sur la Digue où se brisa l'Élan du Flot envahisseur\nNancy, 30 novemiue- — (De notre envoyé spécial.) — En même temps que l'armée èa. général Maunoury arrêtait et repous sait, sur les ç±vam.ps de bataille de l'Ourcq, les troupes allemandes du corps dé von Kluck, une action générale était engagée sur notre front. Depuis les rives de la Marne jusqu'aux bonds de la Médusé' et de la Moselle notre retraite s'était arrêtée et nos troupes fai sant face à l'ennemi reprenaient l'offen sive. Contre la digue solide que constituait nos forces venait sa briser l'élan du flot erwaihisseur eit, .pour la première fois, de- l'ennemi . et dé se replier. Toutes les phases de la lutte engagée depuis le 5 jusqu'au 12 septembre ont revêtu un caractère d'acharnement et fx ' ! —■* A rum n t\"V\npuis le d $but dé la campagne^ l'ennemi était contraint d'interrompre sa marche et -ia «a tôlier. Toutes les Phases de la lutte\ndé à des hommes déjà harassés par 1» longue série de marches et de combata était d'autant plus considérable que lej conditions dians lesquelles ils revenaient sur un adversaire victorieux étaient piuj pénibles. Les chefs eux-mêmes se demandaient, non sans quelque angoisse secrète, si leurs troupes retrouveraient leur élan et leui vaillance après avoir subi la dépression morale et les fatigues physiques suppor tées depuis deu-x mois- : Mais le sentiment qui animait les sol dats, la conscience qu'ils avaient tous da lutter pour la défense de nos libertés exal ta leur courage, décupla leurs fonces les rendit invincmMes. Sur tous les points où se développa, l'of fensive et où s'affirma notre Succès les ac tes d'héroïsme et de dévouement se muiti- ièront. Aussi je ne chercherai pas à dé-\nUnakté admirables. Et l'effort dernan- ' tacher de l'ensemble de ces opérations\nun\n","L'HUMANITÉ\ng*»»\niéjpdsade p(lus particulièrement glorieux. £,& lecture des longues listes de nos cama rades tués ou blessés dans touis les enga gements suffit à montrer que partout l 'es prit de ! vaillance, d'abnégation et de sacri- •liee fut aussi grand et aussi généreux. [.•a, visité rapide que nous venons de : faire sur le terrain où se livrèrent ces ren contres si violentes nous a amplement ; Jp.rouvé combien il avait fallu'déployer d'é nergie et de persévérance pour s'opposer ù la marche de l'ennemi et obliger des ar mées nombreuses, formidablement armées et puissamment conduites, à céder les ré gions qu'elles avaient conquises. Comment se décida le succès Ln choc qui devait briser toute l'ordon- :.aiance stratégique des armées allemandes et disloquer leur front' se produisit à la môme date que celle où l'intervention ra pide de l'armée du général Maunoury s'ef- . 'l'èctuait dans l'Ile de France. ■ C'est le 4 septembre au soir que l'ordre du généralissime d'arrêter la retraite par- > Venait à nos corps d'armée qui se trou vaient disposés sur la longue ligne de l'eu allant die la place forte de Verdun aux avancées de Paris, en passant pas le bas ._ tte l'Argonne, Vitry-le-Francois, Esternay, Courchamp, Villiers-Saint-Georges. '- Cet ordre affirmait la volonté du chef de ne plus regarder en arrière, de se dres ser contre l'ennemi et de tenir^ tête à ses attaques jusqu'au bout, jusqu'à la mort. Aussitôt « l'espoir changea de camp, le combat changea d'âme » et la retraite de l 1 adversaire commença à l'heure même où rétat-major certifiait que nos armées al laient être anéanties. Des témoignages irrécusables Les trois armées des généraux Eraiichet id'Esperey, Foclh et Lanigle de Cary prirent pendant la journée du 5 leurs dispositions jxiur commencer l'attaque le 6. première livra un combat rapide. . F. I.l<s. assaillit les forces adversaires le 6, à 11 heures du matin et vingt-quatre heures après, le 7, à midi, le général Francihet ti'F.aperey avait forcé les Allemands à re çu 1er- . Pour les forces placées sous les ordres du général Foch la lutte fut plus dure. Il leur fallut se battre sans trêve_ pendant trois jours. Les traces de la bataille souli gnent la violence de la mêlée. Les villages die Morains, Normée, Lenharrée, _ qui furent pris et repris, et durent subir le bombardement incessant des deux artille ries, sont tous en ruines ; les champs, les plaines sont troués d'obus et partout gisent encore des projectiles de toutes {sortes. ■ Les rencontres engagées le 6 au matin eurent d'abord pour effet de contraindre les troupes du général Foch. : 11 e et 9 e corps, 21 e division et une division maro caine, à se replier sur Salon et Courtan- son. A ce moment, cette armée n'est plus en liaison avec celle du général Langle ■■de Cary. Elle en est séparée par un « trou » de vingt kilomètres, dans lequel est éparpillée une seule division de cava lerie. Enfoncé à sa gauche, enfoncé au centre, le général Foch décide de repren dre l'offensive sur sa droite et, le 7, il donne comme objectif à ses troupes la position de Fère-Ghampenoise. La ligne Morains, Normée, Lenharrée est reprise et Fère-Champenoise enlevée à onze heu res du matin. L'occupation est si rapide que des officiers de l'état-major allemand non encore .dégrisés, sont faits prison niers. C'est au cours de ces combats que les marais de Saint-Gonid servirent de tom beau à deux régiments de la garde prus sienne. Mais l'intensité de la lutte, qui était allée en s'aggravant pour les corps d'ar mée du général Fôch, devait atteindre son maximum pour les forces du général Langle de Cary. Ces troupes s'étaient ■battues sur la Meuse et v avaient même Obtenu dés succès partiels très importants, •■notamment le 27 août. Elles reculaient cependant pour gagner la place fixée dans la. ligne d'ensemble, sur laquelle le généralissime voulait arrêter la retraite et marcher à son tour sur l'ennemi. Ce sont ces forces, composées du 2° corps, du corps oolondaJ, du 12° et du 17® qui, à Ser- maize, Le Maurupt, Blesmes, Vàuelerc, t'Iuéron, Courdemange et Imbeauville, se trouvèrent aux prises avec cinq corps «l'armée allemands. Les hommes étaient physiquement épui sés par une série de marches qui avaient duré quatorze jours dont dix de combats incessants. Par un prodige de volonté col lective, ces mêmes soldats- se lancèrent à J'attaque. Cinq jours durant, la fusillade, le bombardement firent rage. Les routes, les fossés, les terres, les maisons furent le théâtre de corps à corps terribles. Sur tout le champ de bataille, on avançait, on reculait, on tombait.. La région dans laquelle se tenait la droite de l'armée allemande supporta plus particuliènemenA l'effort de nos troupes, «-'est sur cette partie du vaste champ de bataille que le général amena la majeure partie des régiments dont il disposait et fi laquelle il adjoignit le 21 e corps, prélevé frur les troupes des Vosges, notamment à Spinal. Ce 21 e corps, renforcé d'une divi sion du 12° et d'un© division du corps colonial, fut sévèrement éprouvé. Le 12® le fut encore davantage. Je me bornerai, pour montrer l'étendue de nos gacrificps, à signaler ce fait que les vil lages tte Huéron, Cour'demange, Imbeau- yille, furent, occupés par ce groupe qui se trouva, au plus fort de l'action, réduit à Bix bataillons, sous les ordres du général Roques, et tint tête à tout un corps d'ar- RV&e allemand. La_ fortune fut d'abord variable et la victoire oscilla entre les deux armées pen dant les journées dés 6, 7, -8, 9 et 10 sep tembre. Elle ne se décida que dans la ma tinée du 11. Mais ce jour-là, elle restait dans notre camp : l'héroïsme de nos sol dats l'avait arrachée des mains de nos terribles ennemis. Les troupes de von Bu- la w, le corps saxon et les forces descen dues de Wurtemberg 1 étaient brisées, dis loquée?, tandis que l'armée du kronprinz reculait, entraînant toutes les autres dans Kf). npf.ï'aito\ndans la région du nord\nLe bombardement d'Armentières recommence Les Allemands ont, depuis deux jours, recommencé à bombarder Armentières. Plusieurs tissages ont été incendias. Une briqueterie a été détruite. Le clocher de l'église menace de s'effondrer. La vie industrielle est arrêtée. Un obus ayant fait sauter le gazomètre de l'usine à gaz, la population, dont le nombre est, d'ailleurs, très réduit depuis le dernier exode, est obligée de s'éclairer avec des lampes ou des bougies. Depuis le 27, on souffre du manque d'eau. On» suppose que les Allemands ont coupé les conduites. Une poussée de l'ennemi sur Ârras Vendredi dernier, les Français se sont emparés des villages de Tilloys et de Saint-Laurent, situés à environ quatre ki lomètres au sud-est d'Arras. Cette occu pation indique une progression considéra ble des premières lignes des troupes alliées sur un point- important. Au cours des der nières semaines, l'ennemi s'est livré à des préparatifs considérables. Les Allemands, malgré leurs nombreux échecs, ne sem blent pas avoir abandonné l'espoir d'at teindre la côte. Lorsqu'ils renonceront à leur projet, ils se replieront plus à l'est sur les fortes positions qu'ils ont préparées depuis deux mois. L'infanterie allemande a repris ses atta ques à Ypres, mais tout indique qu'Ar- ras va devenir le centre des opérations de l'ennemi. On annonce qu'il a massé des forces importantes autour de la ville. Au cours des derniers jours, l'artillerie a pré paré l'attaque et Arras a de nouveau souf fert. . Mercredi, les obus allemands ont achevé la destruction de la vieille ville, c'est-à-dire le quartier Saint-Géry, jeudi a commencé le bombardement de ïa ville neuve, et la rue d'Amiens a été presque complètement détruite ; seules quelques maisons restent debout ; vendredi ce fut le tour de la gare ;■ les alliés sont prêts à recevoir le choc de l'ennemi, qui ne réus sira certainement pas à percer nos lignes. Le Bombardement de Reims continue Il a causé des pertes irréparables Le, bombardement de Reims par les 305 autrichiens a été, sur bien des points, meurtrier pour les richesses industrielles et artistiques de la ville. En dehors des ravages irréparables cau sés à la cathédrale, l'artillerie ennemie a démoli plusieurs tissages. Les merveilleu ses tapisseries de Pepersack, l'artisaji fla mand, un des trésors de l'archevêché, ont été la proie du feu. Les pertes totales dé passent 350 millions.\nLe général Mri 11 Alsace\nSA VISITE A THAM«\nLa Bulletin des Armées publie le récit d'une visite faiite par le général Joffre dans la région die l'Alsace occupée par nos troupes et notamment à Tlhanri. Le généralissime félicita les habitants d;e s'être entendus pour assurer avec l'in tendance le ravitaillement, l'assistance et l'administaiation municipale. Voici lés pa roles qu'il prononça ensuite : Notre retour est définitif. Vous êtes Fran çais pour toujours ; la France apporté, avec les libertés qu'elle a toujours représen tées, le respect de vos libertés à vous, des libertés alsaciennes, de vos traditions, de vos convictions, de vos mœurs. , Je suis la France ; vous êtes l'Alsace. Je vous apiporte le baiser de la France. Ces paroles cordiaies, qui s'imprègnent de la pensée de la démocratie, firent battre toutes les mains. La Bataille de l'Yser L'ACTION DE L'ABHÉE BELGE\nDans le dernier numéro du Courrier de l'Armée belge, nous trouvons des rensei gnements intéressants sur la participation de l'armée belge dans la bataille de l'Yser. La bataille de l'Yser a débuté le 16. Le 18 marque le début de l'actioii violente que les Allemands poursuivirent jusqu'au 30 octobre. Après avoir exposé en détail les princi paux faits de guerre, notamment ceux qui se sont passés du 17 au 23 octobre, le Courrier de l Armée conclut : Ainsi, du 17 au 23 octobre, les troupes bel ges, avec l'appoint d'une brigade de fusi liers marins français, résistent seules à la poussée allemande. Du 23 au 30, elles con tinuent la lutte de Nieupo'rt à Dixmude, grâce à l'appoint d'une division française. En donnant aux troupes amies le temps d'intervenir, cette armée, qui .n'avait cessé de combattre pendant deux mois et demi, cette armée, qui n'avait pas disposé d'un seul jour pour sa réorganisation après son habile retraite d'Anvers, a rendu un nouveau et iprécieux service à la cause des alliés. La bataille de l'Yser a été pour elle un incontestable succès, mais combien dure ment acheté ! L'armée belge, dans sa résis tance héroïque sur l'Yser, a Derdu le quart de son effectif. Les Allemands avaient fait des pertes de beaucoup supérieures. Ils aban donnèrent sur le terrain de la lutte leurs morts et leurs blessés, quantité d'armes et de munitions et deux pièces de gros calibre qu'ils avaient portées à l'ouest de l'Yser. et qui furent ramenées parla 1\" division.\nsa, retraite. [A suivre.)\nRaymond F igeac.\nL'APPEL DES TERRITORIAUX En France et en Allemagne iLe Temps publiait Mer la note ci-jointe : On a posé de divers côtés la ' question de savoir si, dans la guerre actuelle, les terri toriaux Tranr.aiR ri£>T+ir>i , no-n+\nJeusgg ûe Prince\nLe Figaro commentait hier la nouvelle que le général da MoltJ.se était en disgrâce. Il pa raîtrait que lé kronprinz se serait plaint de voir le général marclier sur ses brisées et aussi de se livrer, à des critiques dus opéra tions militaires conduites par l'impérial hé ritier. D'où la disgrâce., Le Figaro d'ajouter : a Ce sont là jeux de prince ! » Bravo ! voilà Figaro frondeur — on le savait — redevenu- démocrate et républicain.\n-- a question, la réponse est facile. En droit, tous les territoriaux français astreints exac tement aux mêmes obligations que les ré servistes peuvent être envoyés sur le front ; en fait, une partie seulement de nos divisions territoriales est actuellement dans les tran- çliées ; les autres assurent la garde du terri toire et des places fortes. Le nombre des divisions territoriales fran çaises sur le front est très sensiblement in férieur à celui des divisions territoriales que l'Allemagne a dû envoyer en première ligne. Le nombre de celles-ci (landwehr) est de ■trente, dont seize envoyées contre la France gt quatorze contre la Russie. L'Allemagne a même engagé sur le front ■d'assez nombreuses formations de lands- lurm, c'est-à-dire des hommes plus âgés que les territoriaux français. ; Cette note, <£origine officielle, montre qu'en fait les territo.ria.ux prennent part nie la manière la plus efficace à la défense jxaAi ouate.\nUH APPEL 10 COMITÉ OU SECOURS IAT1IIAL\nLe Comité du Secours National, qui s'est constitué avec l'appui et. l'assentiment du gouvernement, comprend les : représentants de tous les groupements nationaux et de tou tes les forces. sociales de la France. Il a ou vert une souscription s'adressant à tous les Français et aux amis de la France à l'étran ger, pour combattre la misère pendant la guerre. (Jn nouvel effort s'impose au Comité du Secours National. La détresse s'accroît de •jour en jour dans'les départements envahis. En raison de la longueur des hostilités, aux approches de l'hiver, les ressources s'épui sent.. Il faut des secours en nature. Il faut des secours en argent. Le Comité du Secours National fait appel au sentiment de solidarité qui règne entre tous les Français. Les secours qu'il demande sont urgents. Toute la France, pour affirmer son 'unité, doit venir en aide, à la partie de la nation qui souffre pour l'a défendre. Suivent les signatures des membres du Comité),\nSur le Front oriental\nIA BATAILLE DE POLOGNE CONTINUE\nL'IMPÉRÏALISMEl Allemand\nPétrograd, 30 novembre. — Communiqué du grand état-major : Des combats obstinés continuent dans la région de Loviez. La tentative allemande d'avancer dans la région de Szerzow a été repoussée avec de grandes pertes pour l'ennemi. Sur le reste du front, sur la rive gauche de la Vistule, il n'y a eu, le 29 novembre, qu'une simple canonnade. Une défaite autrichienne dans les Karpathes Les troupes russes, après un combot dr. dix -jours, se sont emparées, le 28 novem bre, des positions autrichiennes qui pro tégeaient les passages des Karpathes, sur une étendue de cinquante v'-erstes, depuis Koneczna, au, nord de Bartfeld, au-dessus de Jidowsk et de Jindranown, jusqu'à Sçzuko, au sud de Mezo-Laborez. Elles y ont pris des canons et des mitrailleuses èt y ont fait un grand nombre de prisonniers. Durant la première moitié du mois de novembre, nous avons pris au total 50.000 soldats et 600 officiers austro-hongrois. A Plock, les troupes russes se sont empa rées de quatre embarcations chargées de matériel et de munitions. En Prusse orientale, de petits engage ments continuent à être livrés. Dans la mer Noire, on n'a trouvé trace d'aucun navire turc depuis le 21 novembre. La situation entre la Vistule et la Warta Londres, 1 èr décembre. — Le correspon dant du Times à Pétrograd télégraphie l'exposé suivant de la bataille russo-aEe- mande entre la Vistule et la Warta : La masse de l'armée allemande est disposée su? un front principal d'une étendue de cent milles (160 kilomètres) qui, partant de Sie- radz et passant juste à l'ouest de Lodz et de Lowicz, fait une large courbe. Au centre environ de cette courbe, l'armée allemande occupe un front subsidiaire qui. va, sur une distance de quinze milles, pres que droit vers le sud, en traversant Brzeniny et Buszyn. '•••. Entre Lodz et Lowicz, les Russes qui com bat! eut la gauchie allemande ont livre assaut à Sobota et avancé pour attaquer les posi tions retranchées allemandes à Lee'zyoa, juste en arrière de la principale ligne allemande. La bataille n'est pas encore terminée. La confiance reste absolue ' tondi\\es, 1 er décembre. — Le correspon dant du Morning Post à Pétrograd télé graphie : La confiance reste absolus dans le résultat de la grande bataille ; mais on reconnaît que les troupes russes auront à faire un effort sérieux avant de pouvoir s'emparer des re tranchements allemands, qui sont extrême ment forts. Le correspondant insiste toutefois -sur le fait que les Alleman/ds combattent dans des condiitions défavorables. Le tsar sur le front Pétrograd, ,l or décembre. — Le tsar est parti à 10 heures, ce matin, sur le théâtre de la guerre.\nLA RÉSISTANCE SERBE MARQUE DES PROGRÈS Nisch, 30 novembre. L© 27 novembre, l'ennemi a dirigé des attaques violentes sur le front Maljenrivière de Ljig-Lazare- vatz. Ces attaques ont été particulièrement acharnées contre nos positions établies dans les villages de GoukoChe et Doudo- vatz. L'ennemi a été repoussé sur tout le front. Par trois fois il noifs a attaqués à Goukoche et Chaque f ois il a été repoussé. Nos troupes, passant ensuite à des contre- attaques, ont rejeté l'ennemi vers la ri vière die Ljig. Les attaques dans la région de Douidovatz avaient commencé le 26 au soir et, à ce moment-, l'ennemi avait réussi à occuper un point de la rive droite de la Ljig. Le 27, nos troupes contre-attaquant ont défait l'ennemi et l'ont rejeté au-delà de la rivière. Nous avons fait 3 officiers et 589 soldats prisonniers. • Pendant cette journée du 27 novembre, nous avons fait, sur tous les points du front où ont eu lieu des engagements, un total de 20 officiers et 1.500 soldats prison niers. — (Havas.) UN SUCCES MONTENEGRIN Le communiqué officiel de Cettdgné rap porte qu'un corps autrichien de 10.000 hommes a été. repoussé avec de grandes pertes àr Visegrad. ■\nTRIBUNAUX\nDÉCLARATIONS BU CITOYEN TROELSTRA\nLA GUERRE CONTRE „ , L A TU RQUIE L'OFFENSIVE RUSSE DANS LA VALLÉE DE L'EUPHRATE Pétrograd, 1 er décembre. — Un commu niqué de l'état-major de l'armée du Cau case annonce que la journée d'hier s'est écoulée sans engagements importants. Le 27 novembre, une colonne russe, pre nant l'offensive dans la vallée de l*Euphra- Ite, a délogé les Turcs de leurs positions et les a mis en fuite, capturant deux canons et faisant un certain nombre de prison niers. — {Havas-)\nLE CAS MUSSOLINI\nDébats et Meetings Dana une réunion tenue à Milan la direc tion du Parti socialiste italien a ratifié ïa radiation de Mussolini. Il est cependant intéressant de retenir les réserves faitei par Délia Seta, Zerbini et Marabini qui ont nettement délimité, dans >e cas Mus solini, la question morale et la question morale et la question de discipline. Délia Seta a signalé qu'il fallait tenir compte,. en ce qui concernait l'attitude de l'Italie, que la thèse de la neutralité ab solue était mise à une dure épreuve par la réalîté, : qu'il était, avec Turati, partisan d'une neutralité sympathique à la France et à la Belgique. , :Cette thèse a été soutenue, le même soir, par de nombreux orateurs, dans un mee ting auquel a participé Lazzari, le secré taire du Parti.\nLE LIVRE \"JAUNE\"\n. Amsterdam, 1 er décembre. — Dans le journal H et Volk, organe du Parti socia liste hollandais, le citoyen Pierre Troels- ,tra déclare qu'au cours de son récent voyage en Europe centrale, il a remarqué ;deux courants distincts dans les hautes ('sphères gouvernementales de l'Allemagne. Le premier de ces courants» qui réunit les éléments dits modérés autour du chan celier de l'Empire, a pour le moment la confiance du Kaiser et aussi la sympa thie de la marine. Dans ces milieux, on préconise un impérialisme dirigé princi palement contre l'Angleterre ; et leur porte-parole, l'émipent criminaiiste von Listz, envisage, dans une récente brochure, la formation d'une nouvelle fédération des Etats de l'Europe centrale. La portée des déclarations de M. Zimmermann L'entretien que le citoyen Troelstra eut à Berlin avec le sous-secrétaire d'Etat, M. Zimmermann, démontre que ce projet n'appartient pas seulement au domaine de la spéculation, mais qu'il répond à l'état d'esprit d'importants milieux diplo matiques. J'avais cru, dit Troelstra, que mes com patriotes auraient compris sans commentai res la portée des déclarations de M. Zimmer mann ' disant que l'Allemagne respecterait l'indépendance politique de la Hollande, mais ne pouvait rien lui garantir au point de vue économique. Loin de se réjouir des déclarations de M. Zimmermann comme certains critiques bienveillants semblent vouloir l'inférer de ma première lettre, le projet d'un rapproche ment économique avec lés Pays-Bas est pour moi le point noir des propos que m'a tenus le ministre allemand. J'ai protesté déjà, il y a dix ans, contre le caractère impérialiste d'un pareil rappro chement. Si M. Zimmermann ne parle que d'un rapprochement économique, M. von Listz veut en outre une union douanière et militaire, naturellement. On attendrait la fin de la guerre pour déterminer quels seraient les pays rangés dans la fédération. La nouvelle fédération La fédération comprendrait également les pays Scandinaves et toute la côte oc cidentale de la mer du Nord serait, ainsi placée sous l'influence de l'Allemagne pour lutter contre l'Angleterre. De son côté, le professeur Ostwald a essayé de gagner les pays Scandinaves à l'idée d'une fédération des Etats de la Bal tique dirigée avec la Finlande contre la Russie. Telles sont les idées régnant dans les cercles commerciaux, maritimes et indus triels, chez les hommes des partis de gau che, dans l'entourage du chancelier de l'Empire et des autorités maritimes. Elles ont l'appui du Kaiser. L'alliance des trois empereurs Le second courant observable dans les hautes sphères allemandes préconise l'al liance des trois empereurs allemand, au trichien et russe. Il a pour lui les agra- riens, les désirs de l'état-major et l'en tourage du Kronprinz. En résumé, on peut définir ces deux courants par les qualificatifs suivants : l'un est « impérialiste modernisant », l'au tre « réactionnaire absolutiste ». Tous deux ont pour but la continuation et le développement politique, militariste et pro tectionniste. Pour tous deux, la première étape est d'entraîner les petits Etats- dans une guerre contre l'Angleterre, l'Amérique et le Japon.\nLes commentaires da \" Times \" Londres, 1 er décembre. — Le Times con sacre son éditorial de ce. matin à l'examen générai du « Livre Jaune » français, « qui constitue, dit-il, la (plus importante collec tion de documents officiels, puMiés sur les origines de la guerre. » Après avoir attiré l'attention sur les points principaux, le journal conclut : Le Livre Jaune montre combien la prémé ditation ue la guerre agressive contre la France et la Grande-Bretagne fut longue et délibérée.\nLES SOCIALISTES ET LA (BEIIE Ce que dit Kautsky , Stockholm, 1 er décembre. — On mande de Berlin : : L'écrivain socialiste Karl Kautsky, dit, dans la IV eue Zeit, que les socialistes alle mands n'ont sujet ni de se repentir ni de renier leurs opinions d'avant la guerre, qu'au contraire les événements ont affir mées. Kautsky continue d'espérer dans le pro gramme international de paix ; mais il ne veut rien dire ; sur la possibilité de réaliser pleinement ce orogramme : « Nous n'avons pas pu, dit-il, empêcher la guer re ; nous ne pouvons pas davantage dicter les conditions de paix ». — (Havas.)\nEN A LLEM AGNE DEFENSE DE PORTER LE DEUIL Bdle, l or décembre. — Des personnalités suisses dignes de confiance, qui rentrent d'Allemagne, rapportent que les autorités font les plus grands efforts pour empêcher : la population de se laisser démoraliser. Dans plusieurs des villes où -ces person nes ont passé, notamment à Strabourg et à Cassel, il est interdit de porter le deuil des soldats tués à l'ennemi. Les théâtres sont à dessein restés ouverts et il est re commandé aux fonctionnaires de les fré quenter. — (L'Information.)\nNOUVELLES VOIES FESSÉES STRATÉGIQUES entre Berlin et Cologne Rotterdam, 1 er décembre. — Le Nieuwe Rotterdamsche Courant annonce que huit voies ferrées stratégiques supplémentaires sont posées entre Berlin et Cologne. — (L'Information.)\nAu Bureau Central Postal Militaire\nLa situation de la journée du 29 novembre. Restant de la veille et réception du 29 : Lettres et cartes 1.222-.000 ; j ournaux 4.000 ; mandats 8.800 ; paqtiets et chargements 261.000 ; télégrammes 364.' Restant à trier, le 29 à 20 heures : Let tres et cartes 200.000 ; journaux 300 ; man dats 500 ; paquets et chargements 160.000. ; télégrammes 0. La progression est constante dans le nombre des chargements •• - Le Séquestre d es Maiso ns allemandes Bauscher et Cîe, orfèvres ; Benninghoven, appareils automatiques ; Burstinbinder, four reur ; Dreyfus et liehfeld, commissionnaires en marchandises ; Fischer, tailleur pour da mes : Goldfarb, commissionnaire an mar chandises ! ; Société G'.V.S: moteurs d'autos et d'aéros ; Krebs et Cie, Laudiers, Lankotka, tailleurs ; Linte, tailleur pour dames ; PodetA, fumisterie ; Schaeffert et Badcjiberg, cons truction d'appareils mécaniques ; Schmidt, commissionnaire en marchandises ; Schrae- der, boulanger ; . Voit, bijouterie fausse ; Yung, liôtel d'Autriche. D'autre part, M. Tricheux a été nommé séquestre des marchandises allemandes ou austro-hongroises dans la maison Adler et Lévy ; M. Devisme,» séquestre des marchan das allemandes se trouvant chez M. George Dreyfus, 19, faubourg Saint-Denis ; M. Doyen et. Sï. Gant séquestres des intérêts allemands dans les maisons Goldschmitt et Cie : Hainze et Vie -, M. David expert séquestre de inté rêts allemands dans la Société Philaure, chauffage et. ventilateurs ; Doven séquestre des capitaux et marchandises en dépôt chez MM. Roussette et TQwrna&e.\nLe moratorium ot Ses maisons sous séquestres Le président Monnier a eu hier à trancher une des difficultés que soulève le question de la mise sous séquestre de maisons austro- allemandes. ; On sait que la. Banque privilégiée impé riale autrichienne a été mise soils séquestre. Or, un M. C... qui avait des dépôts dans cette banque prétendit les retirer et la banque lui opposa le moratorium. Il n'est pas possible que le moratorium s'applique à un établissement appartenant ù. une nation ennemie, déclara M C..., et il assigna en référé la banque et le séquestre. Le président Monnier saisi du problème déclara qu'on n'avait pas à examiner la question de savoir si la maison pouvait user du moratorium mais de constater que celle- ci était sous séquestre. « Or, dit le président, il résulte du rapport des séquestres que le mentant des disponibi lités liquides permeUai-î, de verser actuelle ment aux déposants français 50 %, étant en tendu que le reste serait versé au . fur et à mesure des disponibilités ! v — J Û. ■<«■ i i pi i i *i^é——— ■\nACADÉMIE DE MÉDECINE\nContre le Tétanos\nLe docteur Sainton, médecin major de 2° classe, a montré que la méthode de Bac- celli (injection pliéniquée associée au cl'ilo- ral) a une action incontestable sm l'évolu tion du tétanos. Pour que la méthode soit efficace, il est de toute nécessité oue le trai tement soit précoce et appliqué au premier symptôme d'alarme, tel que contracture lo calisée voisine du point d'inoculation. En outre, la médication par le chloral doit tou jours^ être instituée chez les tétaniques, elle constitue une médication symptomatique es sentielle. Tout tétanique qui dort. est un tétanique en voie de guérison. TYPHOÏDE ET OH COLLOÏDAL M. Letulle a décrit une méthode de trai tement de la fièvre typhoïde par des injec tions intraveineuses d'or colloïdal : un quart d'heure après l'injection, le sujet est pris d'un frisson très violent qui diire une di zaine de minutes ; il éprouve ensuite un grand bien-être dont les effets se poursuivent parfois pendant vingt-quatre, trente-six, qua rante-huit heures; Une nouvelle injection fait réapparaître les mêmes phénomènes et peut être, un excellent adjuvant des traitements ordinaires. M. Robin a rappelé qu'il avait appliqué ce traitement dès 1904. POUR LES ENFANTS Après une très longue discussion qui du rait depuis près d'un an, l'Académie a adopté une importante modification à la loi Roussel qui s'applique, on le sait, à la protection des enfants, en bas âge. L'Académie est d'avis au'il y a lieu de ramener de sept mois a quatre mois le mi nimum du temps nendant, lequel une mère doit allaiter son propre enfant avant de se placer comme nourrice;\nLES SPORTS\nFEDERATION SOCIALISTE DE SPORTS ET DE GYMNASTIQUE La Commission administrative porte à la connaissance de tous ses adhérents qu'elle organise, avec' le concours de camarades du Parti, une matinée familiale pour le départ des jeunes de la classe 1915 Des Orateurs du Parti socialiste prendront la parole à cette réunion, qui aura lien le dimanche 6 décembre 1914, salle des fêtes de l'Utilité sociale, 94, boulevard Auguste- Blanqui. Cette réunion étant privée, la carte du Parti sei'a exigée à l'entrée. Invitation cordiale est faite à tous les ca marades. des organisations. — Les matches de football qui devaient avoir lieu. à cette date seront reportés au dimanche 13 décembre 1914, de \" façon à' ce que tous les adhérents puissent \" assister à cette réunion familiale. CONVOCATIONS U. S. et de G. Cervaisïenne, — A 8 h. 30, commission administrative, salle Gaillard, 6, rue de Pantin. <\nPETITE CORRESPONDANCE Anonyme à Mehxm-sur-Yèvre. — Nous ne pensons pa.s pouvoir passer votre souscrip tion sous cette rubrique. Nous sommes prêts à répondre à votre lettre intéressante si vous nous donnez une adresse. Jean Samson. — Nous sommes à peu près d'accord. Chaque chose se fait seulement à son heure, à travers beaucoup de difficultés matérielles, mais elle se fait. Amicalement. NÉCROLOGIE Le citoyen Abelanet-Joffre vient de mourir à Rivesaltes. C'est une perte douloureuse pour cette section où le défunt ne comptait que d'ardentes sympathies. VIENT DE PARAITRE : LES ORIGINES DIPLOMATIQUES DE LA GUERRE (D'après la correspondance du gouvernement britannique) Par Hubert B oijrgin\nEn vente à la Librairie L'exemplaire, franco 0,60.\nd(j l'Humanité.\nl'humanite est composée en commandite par une équipe d'ouvriers syndiqués. .\nLe gérant : G.-A. B ernaud.\nParis, Imp. de la Presse, 16, rue du Croissant: V. S imart , imprimeur. 14 \" ~\nSOCIALE\nCOMMUNICATIONS SYNDICATS Les travailleurs tie l'Etat. — L'Union fé dérale des Travailleurs de l'Etat fait un pressant appel aux syndiqués non mobilisés pour qu'ils assurent le fonctionnement da leur organisation respective. lis pourront correspondre avec la perma nence du secrétariat de l'Union fédérative qui reste assurée à la Bourse du Travail de Paris, rue du Chfiteau-d'Eau, 3. Offi es d'emploi. — Fédération \"s métaux. — Les ouvriers tailleurs de limes en chô* mage sont priés d'envoyer leur adresse rus de la Grange-aux-Belies, 33, au mxi t'ai dl de la Fédération. Voyageurs et représentants de commerça. — MM._ les industriels et commerçants soni informes que le Syndicat national des repré sentants et voyageurs de commerce'.se me* a leur disposition pour leur faciliter !e re crutement du personnel nécessaire à leurs relations_ commerciales ; l'organisation at tue spécialement leur attention sur les apti* tudes professionnelles de ses adhérents. fa adresser au Syndicat national des reprê» sentants et voyageurs de commerce, Boursâ du Travail, Paris. CONVOCATION S REUNIONS PRIVEES SYNDICATS . Boulangers. — Conseil et contrôle, à 9 h., jeudi matin, au siège. PARTI SOCIALISTE Femmes socialistes. — La commission dea travaux pour les soldats prie les camarades d'apporter leurs travaux à l'assemblée du groupe du 6 décembre, 49, rue de Bretagne. •Chorale mixte socialiste. — La réunion est reportée à lundi prochain. 3° section. — A 8 heures, 49, rue de Bre tagne. Réunion générale. 11°, Pupilles. — Commission, chez Duples» sis, à 8 n. 30. 13 e section. — Permanence du trésorier da la caisse de solidarité, de 8 h. 30 à 10 heures» 17, rue Edouard-Manet. Etudiants socialistes révolutionnaires. — A 8 heures, 17, rue Edouard-Manet. Texte de l'appel aux étudiants. 1S\", Grenelle. — A 7 h. 30, salle Franco-\"' Russe, 72, boulevard de Grenelle. Commission des repas populaires. 20°, Jeunesse. —.A S h. 30, rue Malte-Brus» 4. Causerie par A. Luquet. Levallois-Perret. — À 9 heures, 22, rua des Frères-Herbert. Versement à la caisse de solidarité, adresses des mobilisés Vatsves. — A 8 h. 30 du soir, à .la Soupav 96, rue Sadi-Carnot. Les soupes.\nLE\nSAC-PÈLERINE (Nom, modèle et marque déposés)\n»\nen toil© marque R« et C. imperméabilisé© sous I© contrôle d© M. ROUSSEL», Chimiste -Expert\nProtège le Soldai contre Le FROID do couchage La PLUIE païenne. Les PROJECTILES et BAÏONNETTES en l'utilisant comme plastron.\nPoid3 approximatif i kilog. En vente cîiez le Fabricant H. RAULT, 34, Hue S te -Anne, Paria ot dans les principaux Magasins c I d Paris et Provinco. Taille moyenne.. 15 fr. ( par la poste.) Grande Taille ... 16.50 Envoi contre mandat, ajoater le port : Posta recommandé 1.35; Colis postal en gara 0.6G; à iomicila 0.3% les Compagnies n'acceptant pas contre remboorsemeni. Prix Spéciaux pour Sociétés ou Œuvres de Bienfaisanes.\nLe VAINQUEUR de l'Anémie et du Surmenage c'est le Délicieux BAN A NT A la botte 1.40. La double boite 2.50.\nP1FRRES ET ACCESSOIRES CORBRÎON, 87, ras d'Angoalême (Pari») PETITES ANNONCES Alimentation VIW EXTRA 5 9 la pièce, sup. 75 t., éca, grat. T ai < Beauchamp , 96, boulevard Diderot, PARU TRES EPROUVEE financièrement, je garde rai *une sincère reconnaissance ë toute per sonne me prenant sa provision vin rougi que je .céderai à 29 francs l'tieeto, rendu franco ae port et congé payé, fût demeurant votre propriété. Paiement contre remboursa ment net. Juliette BOSC, à Aubais (Gard). Offres et demandes d'emploi Mécaniciens.Tourneurs capables de faire do filetage sont demandés chez F. Turco, 5, rus Bobillot (13°).\nAUCUN FOYER ne devrait être sans P astilles WIUI Ce remède respirable préserve des dangers du froid, de l'Iiumidité, des poussières et des microbes. il assure la GUÉRISON rapide de toutes les maladies de la Gorge, des Bronches et des Poumons* Pour les ENFANTS, pour les ADULTES, comme pour les VIEILLARDS. S ET ADIIBABLE TALISIAI doit avoir sa place dans toutes les familles. Procurez-vous aujourd'hui même UNE BOITE DE PASTILLES VALU mais surtout, EXIGEZ BIEN Im&s 1TERI TABLfiS vendues seulement EN BOITES DE 1.25 portant le nom TALDA\n"],"language":["French"],"identifier":["http://data.theeuropeanlibrary.org/BibliographicResource/3000114597084","http://www.theeuropeanlibrary.org/tel4/newspapers/issue/3000114597084","http://www.theeuropeanlibrary.org/tel4/newspapers/issue/fullscreen/3000114597084","http://gallica.bnf.fr/ark:/12148/bpt6k2540258/f1.thumbnail"]}